{
  "package": "ch.fhir.ig.ch-alis-connect",
  "version": "1.0.0-ballot",
  "fhirVersion": "4.0.1",
  "jurisdiction": "CH",
  "extensions": [
    {
      "url": "http://fhir.ch/ig/ch-alis-connect/StructureDefinition/ch-alis-connect-ext-diagnosisconfidential",
      "title": "CH ALIS Extension DiagnosisConfidential",
      "types": [
        "boolean",
        "boolean"
      ]
    },
    {
      "url": "http://fhir.ch/ig/ch-alis-connect/StructureDefinition/ch-alis-connect-ext-form",
      "title": "CH ALIS Extension Form",
      "types": [
        "string",
        "string"
      ]
    },
    {
      "url": "http://fhir.ch/ig/ch-alis-connect/StructureDefinition/ch-alis-connect-ext-itemnumber",
      "title": "CH ALIS Extension ItemNumber",
      "types": [
        "string",
        "string"
      ]
    },
    {
      "url": "http://fhir.ch/ig/ch-alis-connect/StructureDefinition/ch-alis-connect-ext-orderdate",
      "title": "CH ALIS Extension OrderDate",
      "types": [
        "dateTime",
        "dateTime"
      ]
    },
    {
      "url": "http://fhir.ch/ig/ch-alis-connect/StructureDefinition/ch-alis-connect-ext-orderid",
      "title": "CH ALIS Extension OrderID",
      "types": [
        "string",
        "string"
      ]
    },
    {
      "url": "http://fhir.ch/ig/ch-alis-connect/StructureDefinition/ch-alis-connect-ext-parameterv40",
      "title": "CH ALIS Extension ParameterV40",
      "types": [
        "CodeableConcept",
        "CodeableConcept",
        "string",
        "Extension",
        "Coding",
        "string",
        "Extension",
        "uri",
        "string",
        "code",
        "string",
        "boolean",
        "string",
        "string",
        "string",
        "base64Binary",
        "boolean",
        "canonical",
        "code",
        "date",
        "dateTime",
        "decimal",
        "id",
        "instant",
        "integer",
        "markdown",
        "oid",
        "positiveInt",
        "string",
        "time",
        "unsignedInt",
        "uri",
        "url",
        "uuid",
        "Address",
        "Age",
        "Annotation",
        "Attachment",
        "CodeableConcept",
        "Coding",
        "ContactPoint",
        "Count",
        "Distance",
        "Duration",
        "HumanName",
        "Identifier",
        "Money",
        "Period",
        "Quantity",
        "Range",
        "Ratio",
        "Reference",
        "SampledData",
        "Signature",
        "Timing",
        "ContactDetail",
        "Contributor",
        "DataRequirement",
        "Expression",
        "ParameterDefinition",
        "RelatedArtifact",
        "TriggerDefinition",
        "UsageContext",
        "Dosage",
        "Meta"
      ]
    },
    {
      "url": "http://fhir.ch/ig/ch-alis-connect/StructureDefinition/ch-alis-connect-ext-refitemnumber",
      "title": "CH ALIS Extension RefItemNumber",
      "types": [
        "string",
        "string"
      ]
    },
    {
      "url": "http://fhir.ch/ig/ch-alis-connect/StructureDefinition/ch-alis-connect-ext-sectioncode",
      "title": "CH ALIS Extension SectionCode",
      "types": [
        "Coding",
        "Coding"
      ]
    },
    {
      "url": "http://fhir.ch/ig/ch-alis-connect/StructureDefinition/ch-alis-connect-ext-serviceassignment",
      "title": "CH ALIS Extension ServiceAssignment",
      "types": [
        "string",
        "string",
        "Coding",
        "Coding",
        "dateTime",
        "dateTime",
        "boolean",
        "boolean",
        "base64Binary",
        "boolean",
        "canonical",
        "code",
        "date",
        "dateTime",
        "decimal",
        "id",
        "instant",
        "integer",
        "markdown",
        "oid",
        "positiveInt",
        "string",
        "time",
        "unsignedInt",
        "uri",
        "url",
        "uuid",
        "Address",
        "Age",
        "Annotation",
        "Attachment",
        "CodeableConcept",
        "Coding",
        "ContactPoint",
        "Count",
        "Distance",
        "Duration",
        "HumanName",
        "Identifier",
        "Money",
        "Period",
        "Quantity",
        "Range",
        "Ratio",
        "Reference",
        "SampledData",
        "Signature",
        "Timing",
        "ContactDetail",
        "Contributor",
        "DataRequirement",
        "Expression",
        "ParameterDefinition",
        "RelatedArtifact",
        "TriggerDefinition",
        "UsageContext",
        "Dosage",
        "Meta"
      ]
    },
    {
      "url": "http://fhir.ch/ig/ch-alis-connect/StructureDefinition/ch-alis-connect-ext-serviceitemerrorcode",
      "title": "CH ALIS Extension ServiceItemErrorCode",
      "types": [
        "string",
        "string"
      ]
    },
    {
      "url": "http://fhir.ch/ig/ch-alis-connect/StructureDefinition/ch-alis-connect-ext-sessionannexb",
      "title": "CH ALIS Extension SessionAnnexB",
      "types": [
        "uuid",
        "uuid",
        "base64Binary",
        "boolean",
        "canonical",
        "code",
        "date",
        "dateTime",
        "decimal",
        "id",
        "instant",
        "integer",
        "markdown",
        "oid",
        "positiveInt",
        "string",
        "time",
        "unsignedInt",
        "uri",
        "url",
        "uuid",
        "Address",
        "Age",
        "Annotation",
        "Attachment",
        "CodeableConcept",
        "Coding",
        "ContactPoint",
        "Count",
        "Distance",
        "Duration",
        "HumanName",
        "Identifier",
        "Money",
        "Period",
        "Quantity",
        "Range",
        "Ratio",
        "Reference",
        "SampledData",
        "Signature",
        "Timing",
        "ContactDetail",
        "Contributor",
        "DataRequirement",
        "Expression",
        "ParameterDefinition",
        "RelatedArtifact",
        "TriggerDefinition",
        "UsageContext",
        "Dosage",
        "Meta",
        "uuid",
        "base64Binary",
        "boolean",
        "canonical",
        "code",
        "date",
        "dateTime",
        "decimal",
        "id",
        "instant",
        "integer",
        "markdown",
        "oid",
        "positiveInt",
        "string",
        "time",
        "unsignedInt",
        "uri",
        "url",
        "uuid",
        "Address",
        "Age",
        "Annotation",
        "Attachment",
        "CodeableConcept",
        "Coding",
        "ContactPoint",
        "Count",
        "Distance",
        "Duration",
        "HumanName",
        "Identifier",
        "Money",
        "Period",
        "Quantity",
        "Range",
        "Ratio",
        "Reference",
        "SampledData",
        "Signature",
        "Timing",
        "ContactDetail",
        "Contributor",
        "DataRequirement",
        "Expression",
        "ParameterDefinition",
        "RelatedArtifact",
        "TriggerDefinition",
        "UsageContext",
        "Dosage",
        "Meta"
      ]
    },
    {
      "url": "http://fhir.ch/ig/ch-alis-connect/StructureDefinition/ch-alis-connect-ext-sessionid",
      "title": "CH ALIS Extension SessionID",
      "types": [
        "string",
        "string"
      ]
    },
    {
      "url": "http://fhir.ch/ig/ch-alis-connect/StructureDefinition/ch-alis-connect-ext-termination",
      "title": "CH ALIS Extension Termination",
      "types": [
        "date",
        "date",
        "string",
        "string",
        "base64Binary",
        "boolean",
        "canonical",
        "code",
        "date",
        "dateTime",
        "decimal",
        "id",
        "instant",
        "integer",
        "markdown",
        "oid",
        "positiveInt",
        "string",
        "time",
        "unsignedInt",
        "uri",
        "url",
        "uuid",
        "Address",
        "Age",
        "Annotation",
        "Attachment",
        "CodeableConcept",
        "Coding",
        "ContactPoint",
        "Count",
        "Distance",
        "Duration",
        "HumanName",
        "Identifier",
        "Money",
        "Period",
        "Quantity",
        "Range",
        "Ratio",
        "Reference",
        "SampledData",
        "Signature",
        "Timing",
        "ContactDetail",
        "Contributor",
        "DataRequirement",
        "Expression",
        "ParameterDefinition",
        "RelatedArtifact",
        "TriggerDefinition",
        "UsageContext",
        "Dosage",
        "Meta"
      ]
    },
    {
      "url": "http://fhir.ch/ig/ch-alis-connect/StructureDefinition/ch-alis-connect-ext-tpvalue",
      "title": "CH ALIS Extension TPValue",
      "types": [
        "decimal",
        "decimal"
      ]
    }
  ],
  "profiles": {
    "ChargeItem": [
      {
        "url": "http://fhir.ch/ig/ch-alis-connect/StructureDefinition/ch-alis-connect-chargeitem",
        "title": "CH ALIS ChargeItem Profile"
      }
    ],
    "Condition": [
      {
        "url": "http://fhir.ch/ig/ch-alis-connect/StructureDefinition/ch-alis-connect-condition",
        "title": "CH ALIS Condition Profile"
      }
    ],
    "Encounter": [
      {
        "url": "http://fhir.ch/ig/ch-alis-connect/StructureDefinition/ch-alis-connect-encounter",
        "title": "CH ALIS Encounter Profile"
      }
    ],
    "Patient": [
      {
        "url": "http://fhir.ch/ig/ch-alis-connect/StructureDefinition/ch-alis-connect-patient",
        "title": "CH ALIS Patient Profile"
      }
    ]
  },
  "usage": {
    "http://fhir.ch/ig/ch-alis-connect/StructureDefinition/ch-alis-connect-ext-diagnosisconfidential": [
      "ChargeItem.contained",
      "Condition"
    ],
    "http://fhir.ch/ig/ch-alis-connect/StructureDefinition/ch-alis-connect-ext-form": [
      "ChargeItem"
    ],
    "http://fhir.ch/ig/ch-alis-connect/StructureDefinition/ch-alis-connect-ext-itemnumber": [
      "ChargeItem"
    ],
    "http://fhir.ch/ig/ch-alis-connect/StructureDefinition/ch-alis-connect-ext-orderdate": [
      "ChargeItem"
    ],
    "http://fhir.ch/ig/ch-alis-connect/StructureDefinition/ch-alis-connect-ext-orderid": [
      "ChargeItem"
    ],
    "http://fhir.ch/ig/ch-alis-connect/StructureDefinition/ch-alis-connect-ext-parameterv40": [
      "ChargeItem"
    ],
    "http://fhir.ch/ig/ch-alis-connect/StructureDefinition/ch-alis-connect-ext-refitemnumber": [
      "ChargeItem"
    ],
    "http://fhir.ch/ig/ch-alis-connect/StructureDefinition/ch-alis-connect-ext-sectioncode": [
      "ChargeItem"
    ],
    "http://fhir.ch/ig/ch-alis-connect/StructureDefinition/ch-alis-connect-ext-serviceassignment": [
      "ChargeItem"
    ],
    "http://fhir.ch/ig/ch-alis-connect/StructureDefinition/ch-alis-connect-ext-serviceitemerrorcode": [
      "ChargeItem"
    ],
    "http://fhir.ch/ig/ch-alis-connect/StructureDefinition/ch-alis-connect-ext-sessionannexb": [
      "ChargeItem"
    ],
    "http://fhir.ch/ig/ch-alis-connect/StructureDefinition/ch-alis-connect-ext-sessionid": [
      "ChargeItem"
    ],
    "http://fhir.ch/ig/ch-alis-connect/StructureDefinition/ch-alis-connect-ext-termination": [
      "Encounter"
    ],
    "http://fhir.ch/ig/ch-alis-connect/StructureDefinition/ch-alis-connect-ext-tpvalue": [
      "ChargeItem"
    ],
    "http://fhir.ch/ig/ch-core/StructureDefinition/ch-core-patient-ech-11-placeofbirth": [
      "Patient"
    ],
    "http://fhir.ch/ig/ch-core/StructureDefinition/ch-core-patient-ech-11-placeoforigin": [
      "Patient"
    ],
    "http://fhir.ch/ig/ch-core/StructureDefinition/ch-ext-accident": [
      "Encounter.hospitalization"
    ],
    "http://fhir.ch/ig/ch-core/StructureDefinition/ch-ext-bfs-ms-admitrole": [
      "Encounter.hospitalization"
    ],
    "http://fhir.ch/ig/ch-core/StructureDefinition/ch-ext-bfs-ms-dischargedecision": [
      "Encounter.hospitalization"
    ],
    "http://fhir.ch/ig/ch-core/StructureDefinition/ch-ext-bfs-ms-dischargedestination": [
      "Encounter.hospitalization"
    ],
    "http://fhir.ch/ig/ch-core/StructureDefinition/ch-ext-bfs-ms-encountertype": [
      "Encounter.hospitalization"
    ],
    "http://fhir.ch/ig/ch-core/StructureDefinition/ch-ext-ech-11-firstname": [
      "Patient.name.given"
    ],
    "http://fhir.ch/ig/ch-core/StructureDefinition/ch-ext-ech-11-maritaldata-separation": [
      "Patient.maritalStatus"
    ],
    "http://fhir.ch/ig/ch-core/StructureDefinition/ch-ext-ech-11-name": [
      "Patient.name.family"
    ],
    "http://fhir.ch/ig/ch-core/StructureDefinition/ch-ext-ech-46-emailcategory": [
      "Patient.telecom.use"
    ],
    "http://fhir.ch/ig/ch-core/StructureDefinition/ch-ext-ech-46-internetcategory": [
      "Patient.telecom.use"
    ],
    "http://fhir.ch/ig/ch-core/StructureDefinition/ch-ext-ech-46-phonecategory": [
      "Patient.telecom.use"
    ],
    "http://fhir.ch/ig/ch-core/StructureDefinition/ch-ext-encounter-susp-readmission": [
      "Encounter.hospitalization"
    ],
    "http://fhir.ch/ig/ch-core/StructureDefinition/ch-ext-epl-regulated-authorization-limitation-indication-code": [
      "ChargeItem"
    ],
    "http://hl7.org/fhir/StructureDefinition/elementdefinition-bestpractice": [
      "StructureDefinition.snapshot.element.constraint"
    ],
    "http://hl7.org/fhir/StructureDefinition/elementdefinition-bestpractice-explanation": [
      "StructureDefinition.snapshot.element.constraint"
    ],
    "http://hl7.org/fhir/StructureDefinition/elementdefinition-bindingName": [
      "StructureDefinition.snapshot.element.binding"
    ],
    "http://hl7.org/fhir/StructureDefinition/elementdefinition-maxValueSet": [
      "StructureDefinition.snapshot.element.binding"
    ],
    "http://hl7.org/fhir/StructureDefinition/elementdefinition-namespace": [
      "StructureDefinition"
    ],
    "http://hl7.org/fhir/StructureDefinition/elementdefinition-translatable": [
      "StructureDefinition.snapshot.element"
    ],
    "http://hl7.org/fhir/StructureDefinition/iso21090-EN-qualifier|5.3.0": [
      "Patient.name.prefix"
    ],
    "http://hl7.org/fhir/StructureDefinition/patient-citizenship|5.3.0": [
      "Patient"
    ],
    "http://hl7.org/fhir/StructureDefinition/patient-religion|5.3.0": [
      "Patient"
    ],
    "http://hl7.org/fhir/StructureDefinition/regex": [
      "StructureDefinition.snapshot.element.type"
    ],
    "http://hl7.org/fhir/StructureDefinition/structuredefinition-fhir-type": [
      "StructureDefinition.snapshot.element.type"
    ],
    "http://hl7.org/fhir/StructureDefinition/structuredefinition-hierarchy": [
      "StructureDefinition.snapshot.element.type"
    ],
    "http://hl7.org/fhir/tools/StructureDefinition/ig-internal-dependency": [
      "ImplementationGuide.definition"
    ],
    "http://hl7.org/fhir/tools/StructureDefinition/ig-page-name": [
      "ImplementationGuide.definition.page",
      "ImplementationGuide.definition.page.page"
    ],
    "http://hl7.org/fhir/tools/StructureDefinition/ig-parameter": [
      "ImplementationGuide.definition"
    ],
    "http://hl7.org/fhir/tools/StructureDefinition/implementationguide-dependency-comment": [
      "ImplementationGuide.dependsOn"
    ],
    "http://hl7.org/fhir/tools/StructureDefinition/implementationguide-resource-format": [
      "ImplementationGuide.definition.resource"
    ],
    "http://hl7.org/fhir/tools/StructureDefinition/snapshot-base-version": [
      "StructureDefinition.snapshot"
    ]
  }
}