<?xml version="1.0" encoding="UTF-8"?><Bundle xmlns="http://hl7.org/fhir"><type value="collection"/><entry><resource><OperationOutcome><issue><extension url="http://hl7.org/fhir/StructureDefinition/operationoutcome-issue-source"><valueString value="Publisher"/></extension><severity value="warning"/><code value="business-rule"/><details><text value="The IG is not for the international realm, and it uses SNOMED CT, so it should fix the SCT edition in the expansion parameters"/></details><expression value="IG"/></issue></OperationOutcome></resource></entry><entry><resource><OperationOutcome><extension url="http://hl7.org/fhir/StructureDefinition/operationoutcome-file"><valueString value="/home/runner/work/hl7ch.github.io/hl7ch.github.io/buildtmp/ig-builds/ch.fhir.ig.ch-ig#1.2.2-milestone/fsh-generated/resources/CodeSystem-ch-ig-example"/></extension></OperationOutcome></resource></entry><entry><resource><OperationOutcome><extension url="http://hl7.org/fhir/StructureDefinition/operationoutcome-file"><valueString value="/home/runner/work/hl7ch.github.io/hl7ch.github.io/buildtmp/ig-builds/ch.fhir.ig.ch-ig#1.2.2-milestone/fsh-generated/resources/ImplementationGuide-ch.fhir.ig.ch-ig"/></extension></OperationOutcome></resource></entry><entry><resource><OperationOutcome><extension url="http://hl7.org/fhir/StructureDefinition/operationoutcome-file"><valueString value="/home/runner/work/hl7ch.github.io/hl7ch.github.io/buildtmp/ig-builds/ch.fhir.ig.ch-ig#1.2.2-milestone/fsh-generated/resources/Patient-PetraMeier"/></extension></OperationOutcome></resource></entry><entry><resource><OperationOutcome><extension url="http://hl7.org/fhir/StructureDefinition/operationoutcome-file"><valueString value="/home/runner/work/hl7ch.github.io/hl7ch.github.io/buildtmp/ig-builds/ch.fhir.ig.ch-ig#1.2.2-milestone/fsh-generated/resources/Practitioner-HansMuster"/></extension></OperationOutcome></resource></entry><entry><resource><OperationOutcome><extension url="http://hl7.org/fhir/StructureDefinition/operationoutcome-file"><valueString value="/home/runner/work/hl7ch.github.io/hl7ch.github.io/buildtmp/ig-builds/ch.fhir.ig.ch-ig#1.2.2-milestone/fsh-generated/resources/StructureDefinition-ch-ig-practitioner"/></extension><issue><extension url="http://hl7.org/fhir/StructureDefinition/operationoutcome-issue-line"><valueInteger value="1"/></extension><extension url="http://hl7.org/fhir/StructureDefinition/operationoutcome-issue-col"><valueInteger value="15773"/></extension><extension url="http://hl7.org/fhir/StructureDefinition/operationoutcome-issue-source"><valueString value="InstanceValidator"/></extension><extension url="http://hl7.org/fhir/StructureDefinition/operationoutcome-message-id"><valueCode value="MSG_DEPENDS_ON_DEPRECATED"/></extension><severity value="information"/><code value="business-rule"/><details><text value="The extension http://hl7.org/fhir/StructureDefinition/elementdefinition-maxValueSet|5.2.0 is deprecated"/></details><expression value="StructureDefinition/ch-ig-practitioner: StructureDefinition.snapshot.element[4].binding.extension[0]"/></issue><issue><extension url="http://hl7.org/fhir/StructureDefinition/operationoutcome-issue-source"><valueString value="InstanceValidator"/></extension><severity value="information"/><code value="exception"/><details><text value="The repeating element has a pattern. The pattern will apply to all the repeats (this has not been clear to all users)"/></details><expression value="StructureDefinition/ch-ig-practitioner: StructureDefinition.snapshot.element[11].pattern.ofType(Identifier)"/></issue></OperationOutcome></resource></entry><entry><resource><OperationOutcome><extension url="http://hl7.org/fhir/StructureDefinition/operationoutcome-file"><valueString value="/home/runner/work/hl7ch.github.io/hl7ch.github.io/buildtmp/ig-builds/ch.fhir.ig.ch-ig#1.2.2-milestone/fsh-generated/resources/ValueSet-ch-ig-example"/></extension></OperationOutcome></resource></entry><entry><resource><OperationOutcome><extension url="http://hl7.org/fhir/StructureDefinition/operationoutcome-file"><valueString value="/home/runner/work/hl7ch.github.io/hl7ch.github.io/buildtmp/ig-builds/ch.fhir.ig.ch-ig#1.2.2-milestone/fsh-generated/resources/ValueSet-ch-ig-example-sct"/></extension></OperationOutcome></resource></entry><entry><resource><OperationOutcome><extension url="http://hl7.org/fhir/StructureDefinition/operationoutcome-file"><valueString value="/home/runner/work/hl7ch.github.io/hl7ch.github.io/buildtmp/ig-builds/ch.fhir.ig.ch-ig#1.2.2-milestone/fsh-generated/resources/ValueSet-ch-ig-example-translation"/></extension></OperationOutcome></resource></entry><entry><resource><OperationOutcome><extension url="http://hl7.org/fhir/StructureDefinition/operationoutcome-file"><valueString value="/home/runner/work/hl7ch.github.io/hl7ch.github.io/buildtmp/ig-builds/ch.fhir.ig.ch-ig#1.2.2-milestone/input/resources/CodeSystem-ch-ig-example-translation"/></extension></OperationOutcome></resource></entry></Bundle>