{
  "resourceType" : "ValueSet",
  "id" : "afeb0f49-b57b-449b-88da-6a414d71a394-171",
  "url" : "http://hl7.org/fhir/comparison/ValueSet/afeb0f49-b57b-449b-88da-6a414d71a394-171",
  "name" : "IntersectionChElmInterpretationCodesSeroAndChElmInterpretationCodesSero",
  "title" : "Intersection of CH ELM Interpretation Codes SERO And CH ELM Interpretation Codes SERO",
  "status" : "active",
  "date" : "2025-06-23T21:11:36+00:00",
  "jurisdiction" : [{
    "coding" : [{
      "system" : "urn:iso:std:iso:3166",
      "code" : "CH"
    }]
  }],
  "compose" : {
    "include" : [{
      "concept" : [{
        "code" : "1290194006",
        "display" : "Seroconversion (finding)"
      }]
    }]
  }
}