{
  "resourceType": "NamingSystem",
  "id": "nif",
  "text": {
    "status": "generated",
    "div": "<div xmlns=\"http://www.w3.org/1999/xhtml\">\n      <p>\n        <b>Generated Narrative with Details</b>\n      </p>\n      <p>\n        <b>name</b>: NIF\n      </p>\n      <p>\n        <b>status</b>: ACTIVE\n      </p>\n      <p>\n        <b>kind</b>: IDENTIFIER\n      </p>\n      <p>\n        <b>date</b>: Dec 5, 2018\n      </p>\n      <p>\n        <b>publisher</b>: HL7 Switzerland on behalf of ZAS\n      </p>\n      <p>\n        <b>contact</b>: \n      </p>\n      <p>\n        <b>responsible</b>: ZAS\n      </p>\n      <p>\n        <b>description</b>: Providers of benefits covered by the invalidity insurance receive their own identification number (NIF). See [ZAS](https://www.zas.admin.ch/zas/de/home/partenaires-et-institutions-/paiement-des-prestations-individuelles-avs-ai/information-a-l-attention-des-fournisseurs-de-prestations.html)\n      </p>\n      <p>\n        <b>jurisdiction</b>: Switzerland \n        <span style=\"background: LightGoldenRodYellow\">(Details : {urn:iso:std:iso:3166 code 'CH' = 'Switzerland)</span>\n      </p>\n    </div>"
  },
  "name": "NIF",
  "status": "active",
  "kind": "identifier",
  "date": "2018-12-05T00:00:00+01:00",
  "publisher": "HL7 Switzerland",
  "contact": [
    {
      "name": "HL7 Switzerland",
      "telecom": [
        {
          "system": "url",
          "value": "https://www.hl7.ch/"
        }
      ]
    }
  ],
  "responsible": "ZAS",
  "description": "Providers of benefits covered by the invalidity insurance receive their own identification number (NIF). See [ZAS](https://www.zas.admin.ch/zas/de/home/partenaires-et-institutions-/paiement-des-prestations-individuelles-avs-ai/information-a-l-attention-des-fournisseurs-de-prestations.html)",
  "jurisdiction": [
    {
      "coding": [
        {
          "system": "urn:iso:std:iso:3166",
          "code": "CH"
        }
      ]
    }
  ]
}