{
  "resourceType" : "CodeSystem",
  "id" : "eef8fbb4-584c-4f50-81de-2ca5e0a61bf3-14",
  "url" : "http://hl7.org/fhir/comparison/CodeSystem/eef8fbb4-584c-4f50-81de-2ca5e0a61bf3-14",
  "name" : "UnionChSMCIngredientRoleCSAndChSMCIngredientRoleCS",
  "title" : "Union of CH SMC - Ingredient Role And CH SMC - Ingredient Role",
  "status" : "active",
  "date" : "2025-12-11T12:32:56+00:00",
  "jurisdiction" : [{
    "coding" : [{
      "system" : "urn:iso:std:iso:3166",
      "code" : "CH"
    }]
  }],
  "concept" : [{
    "code" : "756005051001",
    "display" : "Active",
    "designation" : [{
      "language" : "de",
      "use" : {
        "system" : "http://snomed.info/sct",
        "code" : "900000000000003001",
        "display" : "Fully specified name"
      },
      "value" : "Wirkstoff"
    },
    {
      "language" : "de",
      "use" : {
        "system" : "http://snomed.info/sct",
        "code" : "900000000000013009",
        "display" : "Synonym"
      },
      "value" : "WIRKS"
    }]
  },
  {
    "code" : "756005051002",
    "display" : "Excipient",
    "designation" : [{
      "language" : "de",
      "use" : {
        "system" : "http://snomed.info/sct",
        "code" : "900000000000003001",
        "display" : "Fully specified name"
      },
      "value" : "Hilfsstoff"
    },
    {
      "language" : "de",
      "use" : {
        "system" : "http://snomed.info/sct",
        "code" : "900000000000013009",
        "display" : "Synonym"
      },
      "value" : "HNIDK"
    }]
  },
  {
    "code" : "756005051003",
    "display" : "excipient of particular interest",
    "designation" : [{
      "language" : "de",
      "use" : {
        "system" : "http://snomed.info/sct",
        "code" : "900000000000003001",
        "display" : "Fully specified name"
      },
      "value" : "Hilfsstoff von besonderem Interesse"
    },
    {
      "language" : "de",
      "use" : {
        "system" : "http://snomed.info/sct",
        "code" : "900000000000013009",
        "display" : "Synonym"
      },
      "value" : "HBESI"
    }]
  }]
}