<?xml version="1.0" encoding="UTF-8"?>

<ValueSet xmlns="http://hl7.org/fhir">
  <id value="ch-vacd-swissmedic-vaccines-vs"/>
  <text>
    <status value="extensions"/><div xmlns="http://www.w3.org/1999/xhtml"><p class="res-header-id"><b>Generated Narrative: ValueSet ch-vacd-swissmedic-vaccines-vs</b></p><a name="ch-vacd-swissmedic-vaccines-vs"> </a><a name="hcch-vacd-swissmedic-vaccines-vs"> </a><ul><li>Include these codes as defined in <a href="CodeSystem-ch-vacd-swissmedic-cs.html"><code>http://fhir.ch/ig/ch-vacd/CodeSystem/ch-vacd-swissmedic-cs</code></a><span title="Version is not explicitly stated, which means it is fixed to the version provided in this specification"> version &#x1F4E6;3.4.0</span><table class="none"><tr><td style="white-space:nowrap"><b>Code</b></td><td><b>Display</b></td><td><b>Definition</b></td><td><b><a href="ValueSet-ch-vacd-targetdiseasesandillnessesundergoneforimmunization-vs.html">Swissmedic vaccine codes To TargetDisease Mapping</a></b></td><td><b><a href="ConceptMap-ch-vacd-swissmedic-to-nuva-cm.html">ConceptMap for mapping Swissmedic vaccine codes to Nuva codes</a></b></td></tr><tr><td><a href="CodeSystem-ch-vacd-swissmedic-cs.html#ch-vacd-swissmedic-cs-683">683</a></td><td>FSME-Immun 0.25 ml Junior</td><td>FSME-Immun 0.25 ml Junior, Suspension zur intramuskulären Injektion, Pfizer AG</td><td><span title="RELATEDTO">?</span><a href="http://snomed.info/id/712986001">712986001</a></td><td><span title="EQUIVALENT">~</span>VAC0774</td></tr><tr><td><a href="CodeSystem-ch-vacd-swissmedic-cs.html#ch-vacd-swissmedic-cs-450">450</a></td><td>FSME-Immun CC</td><td>FSME-Immun CC, Suspension zur intramuskulären Injektion, Pfizer AG</td><td><span title="RELATEDTO">?</span><a href="http://snomed.info/id/712986001">712986001</a></td><td><span title="EQUIVALENT">~</span>VAC0575</td></tr><tr><td><a href="CodeSystem-ch-vacd-swissmedic-cs.html#ch-vacd-swissmedic-cs-656">656</a></td><td>NeisVac-C</td><td>NeisVac-C, Injektionssuspension, Pfizer AG</td><td><span title="RELATEDTO">?</span><a href="http://snomed.info/id/23511006">23511006</a></td><td><span title="EQUIVALENT">~</span>VAC0850</td></tr><tr><td><a href="CodeSystem-ch-vacd-swissmedic-cs.html#ch-vacd-swissmedic-cs-627">627</a></td><td>Encepur N</td><td>Encepur N, Injektionssuspension, Bavarian Nordic Switzerland AG</td><td><span title="RELATEDTO">?</span><a href="http://snomed.info/id/712986001">712986001</a></td><td><span title="EQUIVALENT">~</span>VAC1483</td></tr><tr><td><a href="CodeSystem-ch-vacd-swissmedic-cs.html#ch-vacd-swissmedic-cs-628">628</a></td><td>Encepur N Kinder / Enfants</td><td>Encepur N Kinder, Injektionssuspension, Bavarian Nordic Switzerland AG</td><td><span title="RELATEDTO">?</span><a href="http://snomed.info/id/712986001">712986001</a></td><td><span title="EQUIVALENT">~</span>VAC1477</td></tr><tr><td><a href="CodeSystem-ch-vacd-swissmedic-cs.html#ch-vacd-swissmedic-cs-572">572</a></td><td>Epaxal</td><td/><td><span title="RELATEDTO">?</span><a href="http://snomed.info/id/40468003">40468003</a></td><td><span title="EQUIVALENT">~</span>VAC0227</td></tr><tr><td><a href="CodeSystem-ch-vacd-swissmedic-cs.html#ch-vacd-swissmedic-cs-544">544</a></td><td>Heprecomb</td><td/><td><span title="RELATEDTO">?</span><a href="http://snomed.info/id/66071002">66071002</a></td><td><span title="EQUIVALENT">~</span>VAC0244</td></tr><tr><td><a href="CodeSystem-ch-vacd-swissmedic-cs.html#ch-vacd-swissmedic-cs-642">642</a></td><td>Heprecomb Kinder</td><td/><td><span title="RELATEDTO">?</span><a href="http://snomed.info/id/66071002">66071002</a></td><td><span title="EQUIVALENT">~</span>VAC1484</td></tr><tr><td><a href="CodeSystem-ch-vacd-swissmedic-cs.html#ch-vacd-swissmedic-cs-614">614</a></td><td>Inflexal V</td><td/><td><span title="RELATEDTO">?</span><a href="http://snomed.info/id/719590007">719590007</a></td><td><span title="EQUIVALENT">~</span>VAC0968</td></tr><tr><td><a href="CodeSystem-ch-vacd-swissmedic-cs.html#ch-vacd-swissmedic-cs-657">657</a></td><td>Menjugate</td><td/><td><span title="RELATEDTO">?</span><a href="http://snomed.info/id/23511006">23511006</a></td><td><span title="EQUIVALENT">~</span>VAC0534</td></tr><tr><td><a href="CodeSystem-ch-vacd-swissmedic-cs.html#ch-vacd-swissmedic-cs-533">533</a></td><td>Moraten</td><td/><td><span title="RELATEDTO">?</span><a href="http://snomed.info/id/14189004">14189004</a></td><td><span title="EQUIVALENT">~</span>VAC0625</td></tr><tr><td><a href="CodeSystem-ch-vacd-swissmedic-cs.html#ch-vacd-swissmedic-cs-555">555</a></td><td>Orochol</td><td/><td><span title="RELATEDTO">?</span><a href="http://snomed.info/id/63650001">63650001</a></td><td><span title="EQUIVALENT">~</span>VAC1094</td></tr><tr><td><a href="CodeSystem-ch-vacd-swissmedic-cs.html#ch-vacd-swissmedic-cs-685">685</a></td><td>Rabipur</td><td>Rabipur, Pulver und Lösungsmittel zur Herstellung einer Injektionslösung in einer Fertigspritze, Bavarian Nordic Berna GmbH</td><td><span title="RELATEDTO">?</span><a href="http://snomed.info/id/14168008">14168008</a></td><td><span title="EQUIVALENT">~</span>VAC0028</td></tr><tr><td><a href="CodeSystem-ch-vacd-swissmedic-cs.html#ch-vacd-swissmedic-cs-702">702</a></td><td>Td-pur</td><td/><td><span title="RELATEDTO">?</span><a href="http://snomed.info/id/76902006">76902006</a><br/><span title="RELATEDTO">?</span><a href="http://snomed.info/id/397430003">397430003</a></td><td><span title="EQUIVALENT">~</span>VAC0993</td></tr><tr><td><a href="CodeSystem-ch-vacd-swissmedic-cs.html#ch-vacd-swissmedic-cs-686">686</a></td><td>Td-Virelon</td><td/><td><span title="RELATEDTO">?</span><a href="http://snomed.info/id/398102009">398102009</a><br/><span title="RELATEDTO">?</span><a href="http://snomed.info/id/76902006">76902006</a><br/><span title="RELATEDTO">?</span><a href="http://snomed.info/id/397430003">397430003</a></td><td><span title="EQUIVALENT">~</span>VAC1497</td></tr><tr><td><a href="CodeSystem-ch-vacd-swissmedic-cs.html#ch-vacd-swissmedic-cs-467">467</a></td><td>Vivotif</td><td>Vivotif, Kapseln, Bavarian Nordic Berna GmbH</td><td><span title="RELATEDTO">?</span><a href="http://snomed.info/id/4834000">4834000</a></td><td><span title="EQUIVALENT">~</span>VAC0451</td></tr><tr><td><a href="CodeSystem-ch-vacd-swissmedic-cs.html#ch-vacd-swissmedic-cs-637">637</a></td><td>Boostrix</td><td/><td><span title="RELATEDTO">?</span><a href="http://snomed.info/id/76902006">76902006</a><br/><span title="RELATEDTO">?</span><a href="http://snomed.info/id/27836007">27836007</a><br/><span title="RELATEDTO">?</span><a href="http://snomed.info/id/397430003">397430003</a></td><td><span title="EQUIVALENT">~</span>VAC0541</td></tr><tr><td><a href="CodeSystem-ch-vacd-swissmedic-cs.html#ch-vacd-swissmedic-cs-681">681</a></td><td>Boostrix Polio</td><td/><td><span title="RELATEDTO">?</span><a href="http://snomed.info/id/398102009">398102009</a><br/><span title="RELATEDTO">?</span><a href="http://snomed.info/id/76902006">76902006</a><br/><span title="RELATEDTO">?</span><a href="http://snomed.info/id/27836007">27836007</a><br/><span title="RELATEDTO">?</span><a href="http://snomed.info/id/397430003">397430003</a></td><td><span title="EQUIVALENT">~</span>VAC0568</td></tr><tr><td><a href="CodeSystem-ch-vacd-swissmedic-cs.html#ch-vacd-swissmedic-cs-567">567</a></td><td>Ditanrix</td><td/><td><span title="RELATEDTO">?</span><a href="http://snomed.info/id/76902006">76902006</a><br/><span title="RELATEDTO">?</span><a href="http://snomed.info/id/397430003">397430003</a></td><td><span title="EQUIVALENT">~</span>VAC0731</td></tr><tr><td><a href="CodeSystem-ch-vacd-swissmedic-cs.html#ch-vacd-swissmedic-cs-551">551</a></td><td>Engerix-B 10</td><td>Engerix-B 10, Injektionssuspension, GlaxoSmithKline AG</td><td><span title="RELATEDTO">?</span><a href="http://snomed.info/id/66071002">66071002</a></td><td><span title="EQUIVALENT">~</span>VAC1057</td></tr><tr><td><a href="CodeSystem-ch-vacd-swissmedic-cs.html#ch-vacd-swissmedic-cs-534">534</a></td><td>Engerix-B 20</td><td>Engerix-B 20, Injektionssuspension, GlaxoSmithKline AG</td><td><span title="RELATEDTO">?</span><a href="http://snomed.info/id/66071002">66071002</a></td><td><span title="EQUIVALENT">~</span>VAC0046</td></tr><tr><td><a href="CodeSystem-ch-vacd-swissmedic-cs.html#ch-vacd-swissmedic-cs-583">583</a></td><td>Fluarix</td><td/><td><span title="RELATEDTO">?</span><a href="http://snomed.info/id/719590007">719590007</a></td><td><span title="EQUIVALENT">~</span>VAC0047</td></tr><tr><td><a href="CodeSystem-ch-vacd-swissmedic-cs.html#ch-vacd-swissmedic-cs-558">558</a></td><td>Havrix 1440</td><td>Havrix 1440, Injektionssuspension, GlaxoSmithKline AG</td><td><span title="RELATEDTO">?</span><a href="http://snomed.info/id/40468003">40468003</a></td><td><span title="EQUIVALENT">~</span>VAC0049</td></tr><tr><td><a href="CodeSystem-ch-vacd-swissmedic-cs.html#ch-vacd-swissmedic-cs-599">599</a></td><td>Havrix 720</td><td>Havrix 720, Injektionssuspension, GlaxoSmithKline AG</td><td><span title="RELATEDTO">?</span><a href="http://snomed.info/id/40468003">40468003</a></td><td><span title="EQUIVALENT">~</span>VAC0050</td></tr><tr><td><a href="CodeSystem-ch-vacd-swissmedic-cs.html#ch-vacd-swissmedic-cs-603">603</a></td><td>Hiberix</td><td>Hiberix, Pulver und Lösungsmittel zur Herstellung einer Injektionslösung, GlaxoSmithKline AG</td><td><span title="RELATEDTO">?</span><a href="http://snomed.info/id/709410003">709410003</a></td><td><span title="EQUIVALENT">~</span>VAC0570</td></tr><tr><td><a href="CodeSystem-ch-vacd-swissmedic-cs.html#ch-vacd-swissmedic-cs-638">638</a></td><td>Infanrix DTPa-IPV</td><td>Infanrix DTPa-IPV, Injektionssuspension, GlaxoSmithKline AG</td><td><span title="RELATEDTO">?</span><a href="http://snomed.info/id/398102009">398102009</a><br/><span title="RELATEDTO">?</span><a href="http://snomed.info/id/76902006">76902006</a><br/><span title="RELATEDTO">?</span><a href="http://snomed.info/id/27836007">27836007</a><br/><span title="RELATEDTO">?</span><a href="http://snomed.info/id/397430003">397430003</a></td><td><span title="EQUIVALENT">~</span>VAC0569</td></tr><tr><td><a href="CodeSystem-ch-vacd-swissmedic-cs.html#ch-vacd-swissmedic-cs-619">619</a></td><td>Infanrix DTPa-IPV+Hib</td><td>Infanrix DTPa-IPV+Hib, Pulver und Suspension zur Herstellung einer Injektionssuspension, GlaxoSmithKline AG</td><td><span title="RELATEDTO">?</span><a href="http://snomed.info/id/709410003">709410003</a><br/><span title="RELATEDTO">?</span><a href="http://snomed.info/id/398102009">398102009</a><br/><span title="RELATEDTO">?</span><a href="http://snomed.info/id/76902006">76902006</a><br/><span title="RELATEDTO">?</span><a href="http://snomed.info/id/27836007">27836007</a><br/><span title="RELATEDTO">?</span><a href="http://snomed.info/id/397430003">397430003</a></td><td><span title="EQUIVALENT">~</span>VAC1045</td></tr><tr><td><a href="CodeSystem-ch-vacd-swissmedic-cs.html#ch-vacd-swissmedic-cs-640">640</a></td><td>Infanrix hexa</td><td>Infanrix hexa, Pulver und Suspension zur Herstellung einer Injektionssuspension, GlaxoSmithKline AG</td><td><span title="RELATEDTO">?</span><a href="http://snomed.info/id/709410003">709410003</a><br/><span title="RELATEDTO">?</span><a href="http://snomed.info/id/66071002">66071002</a><br/><span title="RELATEDTO">?</span><a href="http://snomed.info/id/398102009">398102009</a><br/><span title="RELATEDTO">?</span><a href="http://snomed.info/id/76902006">76902006</a><br/><span title="RELATEDTO">?</span><a href="http://snomed.info/id/27836007">27836007</a><br/><span title="RELATEDTO">?</span><a href="http://snomed.info/id/397430003">397430003</a></td><td><span title="EQUIVALENT">~</span>VAC0014</td></tr><tr><td><a href="CodeSystem-ch-vacd-swissmedic-cs.html#ch-vacd-swissmedic-cs-652">652</a></td><td>Mencevax ACWY</td><td/><td><span title="RELATEDTO">?</span><a href="http://snomed.info/id/23511006">23511006</a><br/><span title="RELATEDTO">?</span><a href="http://snomed.info/id/860805006">860805006</a></td><td><span title="EQUIVALENT">~</span>VAC0018</td></tr><tr><td><a href="CodeSystem-ch-vacd-swissmedic-cs.html#ch-vacd-swissmedic-cs-669">669</a></td><td>Poliorix</td><td/><td><span title="RELATEDTO">?</span><a href="http://snomed.info/id/398102009">398102009</a></td><td><span title="EQUIVALENT">~</span>VAC1488</td></tr><tr><td><a href="CodeSystem-ch-vacd-swissmedic-cs.html#ch-vacd-swissmedic-cs-615">615</a></td><td>Priorix</td><td>Priorix, Pulver und Lösungsmittel zur Herstellung einer Injektionslösung, GlaxoSmithKline AG</td><td><span title="RELATEDTO">?</span><a href="http://snomed.info/id/36653000">36653000</a><br/><span title="RELATEDTO">?</span><a href="http://snomed.info/id/14189004">14189004</a><br/><span title="RELATEDTO">?</span><a href="http://snomed.info/id/36989005">36989005</a></td><td><span title="EQUIVALENT">~</span>VAC0053</td></tr><tr><td><a href="CodeSystem-ch-vacd-swissmedic-cs.html#ch-vacd-swissmedic-cs-592">592</a></td><td>Twinrix 720/20</td><td>Twinrix 720/20, Injektionssuspension, GlaxoSmithKline AG</td><td><span title="RELATEDTO">?</span><a href="http://snomed.info/id/66071002">66071002</a><br/><span title="RELATEDTO">?</span><a href="http://snomed.info/id/40468003">40468003</a></td><td><span title="EQUIVALENT">~</span>VAC0057</td></tr><tr><td><a href="CodeSystem-ch-vacd-swissmedic-cs.html#ch-vacd-swissmedic-cs-585">585</a></td><td>Varilrix</td><td>Varilrix, Pulver und Lösungsmittel zur Herstellung einer Injektionslösung, GlaxoSmithKline AG</td><td><span title="RELATEDTO">?</span><a href="http://snomed.info/id/38907003">38907003</a></td><td><span title="EQUIVALENT">~</span>VAC0060</td></tr><tr><td><a href="CodeSystem-ch-vacd-swissmedic-cs.html#ch-vacd-swissmedic-cs-528">528</a></td><td>Gen H-B-Vax 10</td><td/><td><span title="RELATEDTO">?</span><a href="http://snomed.info/id/66071002">66071002</a></td><td><span title="EQUIVALENT">~</span>VAC1486</td></tr><tr><td><a href="CodeSystem-ch-vacd-swissmedic-cs.html#ch-vacd-swissmedic-cs-545">545</a></td><td>HBVAXPRO 40</td><td>HBVAXPRO 40, Injektionssuspension, MSD Merck Sharp &amp; Dohme AG</td><td><span title="RELATEDTO">?</span><a href="http://snomed.info/id/66071002">66071002</a></td><td><span title="EQUIVALENT">~</span>VAC0010</td></tr><tr><td><a href="CodeSystem-ch-vacd-swissmedic-cs.html#ch-vacd-swissmedic-cs-610">610</a></td><td>Gen H-B-Vax 5</td><td/><td><span title="RELATEDTO">?</span><a href="http://snomed.info/id/66071002">66071002</a></td><td><span title="EQUIVALENT">~</span>VAC1485</td></tr><tr><td><a href="CodeSystem-ch-vacd-swissmedic-cs.html#ch-vacd-swissmedic-cs-663">663</a></td><td>HBVAXPRO 10</td><td>HBVAXPRO 10, Injektionssuspension, MSD Merck Sharp &amp; Dohme AG</td><td><span title="RELATEDTO">?</span><a href="http://snomed.info/id/66071002">66071002</a></td><td><span title="EQUIVALENT">~</span>VAC0009</td></tr><tr><td><a href="CodeSystem-ch-vacd-swissmedic-cs.html#ch-vacd-swissmedic-cs-268">268</a></td><td>MMR-II</td><td/><td><span title="RELATEDTO">?</span><a href="http://snomed.info/id/36653000">36653000</a><br/><span title="RELATEDTO">?</span><a href="http://snomed.info/id/14189004">14189004</a><br/><span title="RELATEDTO">?</span><a href="http://snomed.info/id/36989005">36989005</a></td><td><span title="EQUIVALENT">~</span>VAC0286</td></tr><tr><td><a href="CodeSystem-ch-vacd-swissmedic-cs.html#ch-vacd-swissmedic-cs-247">247</a></td><td>Mumpsvax</td><td/><td><span title="RELATEDTO">?</span><a href="http://snomed.info/id/36989005">36989005</a></td><td><span title="EQUIVALENT">~</span>VAC0315</td></tr><tr><td><a href="CodeSystem-ch-vacd-swissmedic-cs.html#ch-vacd-swissmedic-cs-373">373</a></td><td>Mutagrip</td><td/><td><span title="RELATEDTO">?</span><a href="http://snomed.info/id/719590007">719590007</a></td><td><span title="EQUIVALENT">~</span>VAC0021</td></tr><tr><td><a href="CodeSystem-ch-vacd-swissmedic-cs.html#ch-vacd-swissmedic-cs-613">613</a></td><td>Pentavac</td><td>Pentavac, Poudre et suspension pour suspension injectable, Sanofi-Aventis (Suisse) SA</td><td><span title="RELATEDTO">?</span><a href="http://snomed.info/id/709410003">709410003</a><br/><span title="RELATEDTO">?</span><a href="http://snomed.info/id/398102009">398102009</a><br/><span title="RELATEDTO">?</span><a href="http://snomed.info/id/76902006">76902006</a><br/><span title="RELATEDTO">?</span><a href="http://snomed.info/id/27836007">27836007</a><br/><span title="RELATEDTO">?</span><a href="http://snomed.info/id/397430003">397430003</a></td><td><span title="EQUIVALENT">~</span>VAC0023</td></tr><tr><td><a href="CodeSystem-ch-vacd-swissmedic-cs.html#ch-vacd-swissmedic-cs-509">509</a></td><td>Pneumovax-23</td><td>Pneumovax-23, Injektionslösung in einer Fertigspritze, MSD Merck Sharp &amp; Dohme AG</td><td><span title="RELATEDTO">?</span><a href="http://snomed.info/id/16814004">16814004</a></td><td><span title="EQUIVALENT">~</span>VAC0336</td></tr><tr><td><a href="CodeSystem-ch-vacd-swissmedic-cs.html#ch-vacd-swissmedic-cs-646">646</a></td><td>Revaxis</td><td>Revaxis, suspension injectable, Sanofi-Aventis (Suisse) SA</td><td><span title="RELATEDTO">?</span><a href="http://snomed.info/id/398102009">398102009</a><br/><span title="RELATEDTO">?</span><a href="http://snomed.info/id/76902006">76902006</a><br/><span title="RELATEDTO">?</span><a href="http://snomed.info/id/397430003">397430003</a></td><td><span title="EQUIVALENT">~</span>VAC0030</td></tr><tr><td><a href="CodeSystem-ch-vacd-swissmedic-cs.html#ch-vacd-swissmedic-cs-520">520</a></td><td>Stamaril</td><td>Stamaril, poudre et solvant pour suspension injectable, Sanofi-Aventis (Suisse) SA</td><td><span title="RELATEDTO">?</span><a href="http://snomed.info/id/16541001">16541001</a></td><td><span title="EQUIVALENT">~</span>VAC0035</td></tr><tr><td><a href="CodeSystem-ch-vacd-swissmedic-cs.html#ch-vacd-swissmedic-cs-612">612</a></td><td>Tetravac</td><td>Tetravac, suspension injectable, Sanofi-Aventis (Suisse) SA</td><td><span title="RELATEDTO">?</span><a href="http://snomed.info/id/398102009">398102009</a><br/><span title="RELATEDTO">?</span><a href="http://snomed.info/id/76902006">76902006</a><br/><span title="RELATEDTO">?</span><a href="http://snomed.info/id/27836007">27836007</a><br/><span title="RELATEDTO">?</span><a href="http://snomed.info/id/397430003">397430003</a></td><td><span title="EQUIVALENT">~</span>VAC0037</td></tr><tr><td><a href="CodeSystem-ch-vacd-swissmedic-cs.html#ch-vacd-swissmedic-cs-417">417</a></td><td>Tollwut Impfstoff Mérieux</td><td>Tollwut Impfstoff Mérieux, Poudre et solvant pour suspension injectable, Sanofi-Aventis (Suisse) SA</td><td><span title="RELATEDTO">?</span><a href="http://snomed.info/id/14168008">14168008</a></td><td><span title="EQUIVALENT">~</span>VAC0935</td></tr><tr><td><a href="CodeSystem-ch-vacd-swissmedic-cs.html#ch-vacd-swissmedic-cs-688">688</a></td><td>Varivax</td><td>Varivax, Pulver und Lösungsmittel zur Herstellung einer Injektionssuspension, MSD Merck Sharp &amp; Dohme AG</td><td><span title="RELATEDTO">?</span><a href="http://snomed.info/id/38907003">38907003</a></td><td><span title="EQUIVALENT">~</span>VAC0061</td></tr><tr><td><a href="CodeSystem-ch-vacd-swissmedic-cs.html#ch-vacd-swissmedic-cs-485">485</a></td><td>Influvac</td><td/><td><span title="RELATEDTO">?</span><a href="http://snomed.info/id/719590007">719590007</a></td><td><span title="EQUIVALENT">~</span>VAC0016</td></tr><tr><td><a href="CodeSystem-ch-vacd-swissmedic-cs.html#ch-vacd-swissmedic-cs-660">660</a></td><td>Influvac plus</td><td/><td><span title="RELATEDTO">?</span><a href="http://snomed.info/id/719590007">719590007</a></td><td><span title="EQUIVALENT">~</span>VAC0016</td></tr><tr><td><a href="CodeSystem-ch-vacd-swissmedic-cs.html#ch-vacd-swissmedic-cs-654">654</a></td><td>Meningitec</td><td/><td><span title="RELATEDTO">?</span><a href="http://snomed.info/id/23511006">23511006</a></td><td><span title="EQUIVALENT">~</span>VAC0019</td></tr><tr><td><a href="CodeSystem-ch-vacd-swissmedic-cs.html#ch-vacd-swissmedic-cs-643">643</a></td><td>Prevenar-7</td><td/><td><span title="RELATEDTO">?</span><a href="http://snomed.info/id/16814004">16814004</a></td><td><span title="EQUIVALENT">~</span>VAC1487</td></tr><tr><td><a href="CodeSystem-ch-vacd-swissmedic-cs.html#ch-vacd-swissmedic-cs-644">644</a></td><td>Hexavac</td><td/><td><span title="RELATEDTO">?</span><a href="http://snomed.info/id/709410003">709410003</a><br/><span title="RELATEDTO">?</span><a href="http://snomed.info/id/66071002">66071002</a><br/><span title="RELATEDTO">?</span><a href="http://snomed.info/id/398102009">398102009</a><br/><span title="RELATEDTO">?</span><a href="http://snomed.info/id/76902006">76902006</a><br/><span title="RELATEDTO">?</span><a href="http://snomed.info/id/27836007">27836007</a><br/><span title="RELATEDTO">?</span><a href="http://snomed.info/id/397430003">397430003</a></td><td><span title="EQUIVALENT">~</span>VAC0098</td></tr><tr><td><a href="CodeSystem-ch-vacd-swissmedic-cs.html#ch-vacd-swissmedic-cs-711">711</a></td><td>DiTe pediatric adsorbed</td><td/><td><span title="RELATEDTO">?</span><a href="http://snomed.info/id/76902006">76902006</a><br/><span title="RELATEDTO">?</span><a href="http://snomed.info/id/397430003">397430003</a></td><td><span title="EQUIVALENT">~</span>VAC0963</td></tr><tr><td><a href="CodeSystem-ch-vacd-swissmedic-cs.html#ch-vacd-swissmedic-cs-711-01">711-01</a></td><td>Diphtherie- und Tetanus-Adsorbatimpfstoff für Kinder unter 8 Jahren</td><td>Diphtherie- und Tetanus-Adsorbatimpfstoff für Kinder unter 8 Jahren, Injektionssuspension, Emergent BioSolutions Berna GmbH</td><td><span title="RELATEDTO">?</span><a href="http://snomed.info/id/76902006">76902006</a><br/><span title="RELATEDTO">?</span><a href="http://snomed.info/id/397430003">397430003</a></td><td><span title="EQUIVALENT">~</span>VAC0137</td></tr><tr><td><a href="CodeSystem-ch-vacd-swissmedic-cs.html#ch-vacd-swissmedic-cs-711-02">711-02</a></td><td>Diphtherie- und Tetanus-Adsorbatimpfstoff für Erwachsene und Kinder ab 7 Jahren</td><td>Diphtherie- und Tetanus-Adsorbatimpfstoff für Erwachsene und Kinder ab 7 Jahren, Injektionssuspension, Emergent BioSolutions Berna GmbH</td><td><span title="RELATEDTO">?</span><a href="http://snomed.info/id/76902006">76902006</a><br/><span title="RELATEDTO">?</span><a href="http://snomed.info/id/397430003">397430003</a></td><td><span title="EQUIVALENT">~</span>VAC0920</td></tr><tr><td><a href="CodeSystem-ch-vacd-swissmedic-cs.html#ch-vacd-swissmedic-cs-704">704</a></td><td>Dukoral</td><td/><td><span title="RELATEDTO">?</span><a href="http://snomed.info/id/63650001">63650001</a></td><td><span title="EQUIVALENT">~</span>VAC0005</td></tr><tr><td><a href="CodeSystem-ch-vacd-swissmedic-cs.html#ch-vacd-swissmedic-cs-483">483</a></td><td>Rimevax</td><td/><td><span title="RELATEDTO">?</span><a href="http://snomed.info/id/14189004">14189004</a></td><td><span title="EQUIVALENT">~</span>VAC0359</td></tr><tr><td><a href="CodeSystem-ch-vacd-swissmedic-cs.html#ch-vacd-swissmedic-cs-707">707</a></td><td>Tetanol pur</td><td/><td><span title="RELATEDTO">?</span><a href="http://snomed.info/id/76902006">76902006</a></td><td><span title="EQUIVALENT">~</span>VAC0530</td></tr><tr><td><a href="CodeSystem-ch-vacd-swissmedic-cs.html#ch-vacd-swissmedic-cs-57735">57735</a></td><td>Gardasil</td><td/><td><span title="RELATEDTO">?</span><a href="http://snomed.info/id/240532009">240532009</a></td><td><span title="EQUIVALENT">~</span>VAC0007</td></tr><tr><td><a href="CodeSystem-ch-vacd-swissmedic-cs.html#ch-vacd-swissmedic-cs-709">709</a></td><td>Zostavax</td><td/><td><span title="RELATEDTO">?</span><a href="http://snomed.info/id/4740000">4740000</a></td><td><span title="EQUIVALENT">~</span>VAC0161</td></tr><tr><td><a href="CodeSystem-ch-vacd-swissmedic-cs.html#ch-vacd-swissmedic-cs-58158">58158</a></td><td>Priorix-Tetra</td><td>Priorix, Pulver und Lösungsmittel zur Herstellung einer Injektionslösung, GlaxoSmithKline AG</td><td><span title="RELATEDTO">?</span><a href="http://snomed.info/id/38907003">38907003</a><br/><span title="RELATEDTO">?</span><a href="http://snomed.info/id/36653000">36653000</a><br/><span title="RELATEDTO">?</span><a href="http://snomed.info/id/14189004">14189004</a><br/><span title="RELATEDTO">?</span><a href="http://snomed.info/id/36989005">36989005</a></td><td><span title="EQUIVALENT">~</span>VAC0121</td></tr><tr><td><a href="CodeSystem-ch-vacd-swissmedic-cs.html#ch-vacd-swissmedic-cs-696">696</a></td><td>BCG SSI</td><td/><td><span title="RELATEDTO">?</span><a href="http://snomed.info/id/56717001">56717001</a></td><td><span title="EQUIVALENT">~</span>VAC0042</td></tr><tr><td><a href="CodeSystem-ch-vacd-swissmedic-cs.html#ch-vacd-swissmedic-cs-58317">58317</a></td><td>Fluad</td><td/><td><span title="RELATEDTO">?</span><a href="http://snomed.info/id/719590007">719590007</a></td><td><span title="EQUIVALENT">~</span>VAC0230</td></tr><tr><td><a href="CodeSystem-ch-vacd-swissmedic-cs.html#ch-vacd-swissmedic-cs-60150">60150</a></td><td>Rotarix</td><td>Rotarix liquid, orale Suspension, GlaxoSmithKline AG</td><td><span title="RELATEDTO">?</span><a href="http://snomed.info/id/18624000">18624000</a></td><td><span title="EQUIVALENT">~</span>VAC0514</td></tr><tr><td><a href="CodeSystem-ch-vacd-swissmedic-cs.html#ch-vacd-swissmedic-cs-703">703</a></td><td>MMRVaxPro</td><td>M-M-RVAXPRO, Pulver und Lösungsmittel zur Herstellung einer Injektionssuspension, MSD Merck Sharp &amp; Dohme AG</td><td><span title="RELATEDTO">?</span><a href="http://snomed.info/id/36653000">36653000</a><br/><span title="RELATEDTO">?</span><a href="http://snomed.info/id/14189004">14189004</a><br/><span title="RELATEDTO">?</span><a href="http://snomed.info/id/36989005">36989005</a></td><td><span title="EQUIVALENT">~</span>VAC0017</td></tr><tr><td><a href="CodeSystem-ch-vacd-swissmedic-cs.html#ch-vacd-swissmedic-cs-58506">58506</a></td><td>Measles vaccine live</td><td/><td><span title="RELATEDTO">?</span><a href="http://snomed.info/id/14189004">14189004</a></td><td><span title="EQUIVALENT">~</span>VAC0114</td></tr><tr><td><a href="CodeSystem-ch-vacd-swissmedic-cs.html#ch-vacd-swissmedic-cs-59267">59267</a></td><td>Agrippal</td><td/><td><span title="RELATEDTO">?</span><a href="http://snomed.info/id/719590007">719590007</a></td><td><span title="EQUIVALENT">~</span>VAC0002</td></tr><tr><td><a href="CodeSystem-ch-vacd-swissmedic-cs.html#ch-vacd-swissmedic-cs-58271">58271</a></td><td>Optaflu</td><td/><td><span title="RELATEDTO">?</span><a href="http://snomed.info/id/719590007">719590007</a></td><td><span title="EQUIVALENT">~</span>VAC0169</td></tr><tr><td><a href="CodeSystem-ch-vacd-swissmedic-cs.html#ch-vacd-swissmedic-cs-57814">57814</a></td><td>Cervarix</td><td/><td><span title="RELATEDTO">?</span><a href="http://snomed.info/id/240532009">240532009</a></td><td><span title="EQUIVALENT">~</span>VAC0044</td></tr><tr><td><a href="CodeSystem-ch-vacd-swissmedic-cs.html#ch-vacd-swissmedic-cs-60129">60129</a></td><td>Prevenar 13</td><td>Prevenar 13, Injektionssuspension in einer Fertigspritze, Pfizer AG</td><td><span title="RELATEDTO">?</span><a href="http://snomed.info/id/16814004">16814004</a></td><td><span title="EQUIVALENT">~</span>VAC0123</td></tr><tr><td><a href="CodeSystem-ch-vacd-swissmedic-cs.html#ch-vacd-swissmedic-cs-59147">59147</a></td><td>Ixiaro</td><td>IXIARO, Injektionssuspension, Future Health Pharma GmbH</td><td><span title="RELATEDTO">?</span><a href="http://snomed.info/id/52947006">52947006</a></td><td><span title="EQUIVALENT">~</span>VAC0073</td></tr><tr><td><a href="CodeSystem-ch-vacd-swissmedic-cs.html#ch-vacd-swissmedic-cs-62502">62502</a></td><td>Menveo</td><td>Menveo, Pulver und Lösung (Durchstechflaschen), GlaxoSmithKline AG</td><td><span title="RELATEDTO">?</span><a href="http://snomed.info/id/23511006">23511006</a></td><td><span title="EQUIVALENT">~</span>VAC0141</td></tr><tr><td><a href="CodeSystem-ch-vacd-swissmedic-cs.html#ch-vacd-swissmedic-cs-600">600</a></td><td>DiTe Anatoxal Erwachsene / Adultes</td><td/><td><span title="RELATEDTO">?</span><a href="http://snomed.info/id/76902006">76902006</a><br/><span title="RELATEDTO">?</span><a href="http://snomed.info/id/397430003">397430003</a></td><td><span title="EQUIVALENT">~</span>VAC0216</td></tr><tr><td><a href="CodeSystem-ch-vacd-swissmedic-cs.html#ch-vacd-swissmedic-cs-690">690</a></td><td>DiTe Anatoxal N Erwachsene / Adultes</td><td/><td><span title="RELATEDTO">?</span><a href="http://snomed.info/id/76902006">76902006</a><br/><span title="RELATEDTO">?</span><a href="http://snomed.info/id/397430003">397430003</a></td><td><span title="EQUIVALENT">~</span>VAC0962</td></tr><tr><td><a href="CodeSystem-ch-vacd-swissmedic-cs.html#ch-vacd-swissmedic-cs-689">689</a></td><td>Te Anatoxal N</td><td/><td><span title="RELATEDTO">?</span><a href="http://snomed.info/id/76902006">76902006</a></td><td><span title="EQUIVALENT">~</span>VAC0961</td></tr><tr><td><a href="CodeSystem-ch-vacd-swissmedic-cs.html#ch-vacd-swissmedic-cs-62961">62961</a></td><td>Fluarix Tetra</td><td>Fluarix Tetra 15 µg / 0.5 ml, Injektionssuspension, GlaxoSmithKline AG</td><td><span title="RELATEDTO">?</span><a href="http://snomed.info/id/719590007">719590007</a></td><td><span title="EQUIVALENT">~</span>VAC0517</td></tr><tr><td><a href="CodeSystem-ch-vacd-swissmedic-cs.html#ch-vacd-swissmedic-cs-66037">66037</a></td><td>Menjugate liquid</td><td/><td><span title="RELATEDTO">?</span><a href="http://snomed.info/id/860805006">860805006</a></td><td><span title="EQUIVALENT">~</span>VAC0534</td></tr><tr><td><a href="CodeSystem-ch-vacd-swissmedic-cs.html#ch-vacd-swissmedic-cs-699">699</a></td><td>ProQuad</td><td>ProQuad, Pulver und Lösungsmittel zur Herstellung einer Injektionssuspension, MSD Merck Sharp &amp; Dohme AG</td><td><span title="RELATEDTO">?</span><a href="http://snomed.info/id/36653000">36653000</a><br/><span title="RELATEDTO">?</span><a href="http://snomed.info/id/14189004">14189004</a><br/><span title="RELATEDTO">?</span><a href="http://snomed.info/id/36989005">36989005</a><br/><span title="RELATEDTO">?</span><a href="http://snomed.info/id/38907003">38907003</a></td><td><span title="EQUIVALENT">~</span>VAC0174</td></tr><tr><td><a href="CodeSystem-ch-vacd-swissmedic-cs.html#ch-vacd-swissmedic-cs-65728">65728</a></td><td>Gardasil 9 (Durchstechflasche)</td><td>Gardasil 9, Injektionssuspension in Durchstechflasche, MSD Merck Sharp &amp; Dohme AG</td><td><span title="RELATEDTO">?</span><a href="http://snomed.info/id/240532009">240532009</a></td><td/></tr><tr><td><a href="CodeSystem-ch-vacd-swissmedic-cs.html#ch-vacd-swissmedic-cs-65387">65387</a></td><td>Gardasil 9</td><td>Gardasil 9, Injektionssuspension in Fertigspritze,	MSD Merck Sharp &amp; Dohme AG</td><td><span title="RELATEDTO">?</span><a href="http://snomed.info/id/240532009">240532009</a></td><td><span title="EQUIVALENT">~</span>VAC0523</td></tr><tr><td><a href="CodeSystem-ch-vacd-swissmedic-cs.html#ch-vacd-swissmedic-cs-66940">66940</a></td><td>Vaxelis</td><td>Vaxelis 0.5 ml, Injektionssuspension, Future Health Pharma GmbH</td><td><span title="RELATEDTO">?</span><a href="http://snomed.info/id/76902006">76902006</a><br/><span title="RELATEDTO">?</span><a href="http://snomed.info/id/27836007">27836007</a><br/><span title="RELATEDTO">?</span><a href="http://snomed.info/id/398102009">398102009</a><br/><span title="RELATEDTO">?</span><a href="http://snomed.info/id/397430003">397430003</a><br/><span title="RELATEDTO">?</span><a href="http://snomed.info/id/66071002">66071002</a><br/><span title="RELATEDTO">?</span><a href="http://snomed.info/id/709410003">709410003</a></td><td><span title="EQUIVALENT">~</span>VAC0535</td></tr><tr><td><a href="CodeSystem-ch-vacd-swissmedic-cs.html#ch-vacd-swissmedic-cs-66427">66427</a></td><td>VaxigripTetra</td><td>VaxigripTetra, Suspension pour injection dans une seringue pré-remplie, Sanofi-Aventis (Suisse) SA</td><td><span title="RELATEDTO">?</span><a href="http://snomed.info/id/719590007">719590007</a></td><td><span title="EQUIVALENT">~</span>VAC0560</td></tr><tr><td><a href="CodeSystem-ch-vacd-swissmedic-cs.html#ch-vacd-swissmedic-cs-65730">65730</a></td><td>Bexsero</td><td>Bexsero, Injektionssuspension, GlaxoSmithKline AG</td><td><span title="RELATEDTO">?</span><a href="http://snomed.info/id/23511006">23511006</a></td><td><span title="EQUIVALENT">~</span>VAC0495</td></tr><tr><td><a href="CodeSystem-ch-vacd-swissmedic-cs.html#ch-vacd-swissmedic-cs-68087">68087</a></td><td>Influvac Tetra</td><td>Influvac Tetra 0.5 ml, Injektionssuspension, Mylan Pharma GmbH</td><td><span title="RELATEDTO">?</span><a href="http://snomed.info/id/719590007">719590007</a></td><td><span title="EQUIVALENT">~</span>VAC0562</td></tr><tr><td><a href="CodeSystem-ch-vacd-swissmedic-cs.html#ch-vacd-swissmedic-cs-68267">68267</a></td><td>Spikevax (COVID-19 Vaccine, Moderna)</td><td>Spikevax, Injektionsdispersion, Moderna Switzerland GmbH</td><td><span title="RELATEDTO">?</span><a href="http://snomed.info/id/840539006">840539006</a></td><td><span title="EQUIVALENT">~</span>VAC1019</td></tr><tr><td><a href="CodeSystem-ch-vacd-swissmedic-cs.html#ch-vacd-swissmedic-cs-68225">68225</a></td><td>Comirnaty (COVID-19 Vaccine, Pfizer)</td><td>Comirnaty, Konzentrat zur Herstellung einer Injektionsdispersion, Pfizer AG</td><td><span title="RELATEDTO">?</span><a href="http://snomed.info/id/840539006">840539006</a></td><td><span title="EQUIVALENT">~</span>VAC0658</td></tr><tr><td><a href="CodeSystem-ch-vacd-swissmedic-cs.html#ch-vacd-swissmedic-cs-68235">68235</a></td><td>COVID-19 Vaccine Janssen</td><td>COVID-19 Vaccine Janssen, Injektionssuspension, Janssen-Cilag AG</td><td><span title="RELATEDTO">?</span><a href="http://snomed.info/id/840539006">840539006</a></td><td><span title="EQUIVALENT">~</span>VAC0666</td></tr><tr><td><a href="CodeSystem-ch-vacd-swissmedic-cs.html#ch-vacd-swissmedic-cs-67987">67987</a></td><td>Shingrix</td><td>Shingrix, Pulver und Suspension zur Herstellung einer Injektionssuspension, GlaxoSmithKline AG</td><td><span title="RELATEDTO">?</span><a href="http://snomed.info/id/4740000">4740000</a></td><td><span title="EQUIVALENT">~</span>VAC0567</td></tr><tr><td><a href="CodeSystem-ch-vacd-swissmedic-cs.html#ch-vacd-swissmedic-cs-67482">67482</a></td><td>Flucelvax Tetra</td><td>Flucelvax Tetra, Injektionssuspension, Medius AG</td><td><span title="RELATEDTO">?</span><a href="http://snomed.info/id/719590007">719590007</a></td><td><span title="EQUIVALENT">~</span>VAC0595</td></tr><tr><td><a href="CodeSystem-ch-vacd-swissmedic-cs.html#ch-vacd-swissmedic-cs-67704">67704</a></td><td>Efluelda 0.7 ml</td><td>Efluelda 0.7 ml, suspension injectable en seringue préremplie, Sanofi-Aventis (Suisse) SA</td><td><span title="RELATEDTO">?</span><a href="http://snomed.info/id/719590007">719590007</a></td><td><span title="EQUIVALENT">~</span>VAC0649</td></tr><tr><td><a href="CodeSystem-ch-vacd-swissmedic-cs.html#ch-vacd-swissmedic-cs-68003">68003</a></td><td>Supemtek 0.5 ml</td><td>Supemtek 0.5 ml, solution injectable dans une seringue pré-remplie, Sanofi-Aventis (Suisse) SA</td><td><span title="RELATEDTO">?</span><a href="http://snomed.info/id/719590007">719590007</a></td><td><span title="EQUIVALENT">~</span>VAC0871</td></tr><tr><td><a href="CodeSystem-ch-vacd-swissmedic-cs.html#ch-vacd-swissmedic-cs-66161">66161</a></td><td>Foclivia (Durchstechflasche)</td><td>Foclivia, Injektionssuspension in einer Durchstechflasche, Emergent BioSolutions Berna GmbH</td><td><span title="RELATEDTO">?</span><a href="http://snomed.info/id/719865001">719865001</a></td><td><span title="EQUIVALENT">~</span>VAC0475</td></tr><tr><td><a href="CodeSystem-ch-vacd-swissmedic-cs.html#ch-vacd-swissmedic-cs-66156">66156</a></td><td>Foclivia (Fertigspritze)</td><td>Foclivia, Injektionssuspension in einer Fertigspritze, Emergent BioSolutions Berna GmbH</td><td><span title="RELATEDTO">?</span><a href="http://snomed.info/id/719865001">719865001</a></td><td><span title="EQUIVALENT">~</span>VAC0475</td></tr><tr><td><a href="CodeSystem-ch-vacd-swissmedic-cs.html#ch-vacd-swissmedic-cs-68473">68473</a></td><td>Nuvaxovid 0.5 ml</td><td>Nuvaxovid 0.5 ml, Injektionsdispersion, Future Health Pharma GmbH</td><td><span title="RELATEDTO">?</span><a href="http://snomed.info/id/840539006">840539006</a></td><td><span title="EQUIVALENT">~</span>VAC0667</td></tr><tr><td><a href="CodeSystem-ch-vacd-swissmedic-cs.html#ch-vacd-swissmedic-cs-68358">68358</a></td><td>Ervebo</td><td>Ervebo, Injektionslösung, MSD Merck Sharp &amp; Dohme AG</td><td><span title="RELATEDTO">?</span><a href="http://snomed.info/id/37109004">37109004</a></td><td><span title="EQUIVALENT">~</span>VAC0586</td></tr><tr><td><a href="CodeSystem-ch-vacd-swissmedic-cs.html#ch-vacd-swissmedic-cs-68710-01">68710-01</a></td><td>Comirnaty® 30 Mikrogramm/Dosis</td><td>Comirnaty® 30 Mikrogramm/Dosis, gebrauchsfertige Injektionsdispersion für Personen ab 12 Jahren, Pfizer AG</td><td><span title="RELATEDTO">?</span><a href="http://snomed.info/id/840539006">840539006</a></td><td><span title="EQUIVALENT">~</span>VAC0658</td></tr><tr><td><a href="CodeSystem-ch-vacd-swissmedic-cs.html#ch-vacd-swissmedic-cs-68710-02">68710-02</a></td><td>Comirnaty® 10 Mikrogramm/Dosis</td><td>Comirnaty® 10 Mikrogramm/Dosis, Konzentrat zur Herstellung einer Injektionsdispersion, Pfizer AG</td><td><span title="RELATEDTO">?</span><a href="http://snomed.info/id/840539006">840539006</a></td><td><span title="EQUIVALENT">~</span>VAC0833</td></tr><tr><td><a href="CodeSystem-ch-vacd-swissmedic-cs.html#ch-vacd-swissmedic-cs-68710-03">68710-03</a></td><td>Comirnaty® 3 Mikrogramm/Dosis</td><td>Comirnaty® 3 Mikrogramm/Dosis, Konzentrat zur Herstellung einer Injektionsdispersion, Pfizer AG</td><td><span title="RELATEDTO">?</span><a href="http://snomed.info/id/840539006">840539006</a></td><td><span title="EQUIVALENT">~</span>VAC1022</td></tr><tr><td><a href="CodeSystem-ch-vacd-swissmedic-cs.html#ch-vacd-swissmedic-cs-68462">68462</a></td><td>Fluenz Tetra</td><td>Fluenz Tetra, Nasenspray, Suspension, AstraZeneca AG</td><td><span title="RELATEDTO">?</span><a href="http://snomed.info/id/719590007">719590007</a></td><td><span title="EQUIVALENT">~</span>VAC0521</td></tr><tr><td><a href="CodeSystem-ch-vacd-swissmedic-cs.html#ch-vacd-swissmedic-cs-69009">69009</a></td><td>Spikevax Bivalent Original / Omicron</td><td>Spikevax Bivalent Original / Omicron, Moderna Switzerland GmbH</td><td><span title="RELATEDTO">?</span><a href="http://snomed.info/id/840539006">840539006</a></td><td><span title="EQUIVALENT">~</span>VAC1017</td></tr><tr><td><a href="CodeSystem-ch-vacd-swissmedic-cs.html#ch-vacd-swissmedic-cs-68110">68110</a></td><td>Adacel-Polio 0.5 ml</td><td>Adacel-Polio 0.5 ml, suspension injectable en seringue préremplie, Sanofi-Aventis (Suisse) SA</td><td><span title="RELATEDTO">?</span><a href="http://snomed.info/id/398102009">398102009</a><br/><span title="RELATEDTO">?</span><a href="http://snomed.info/id/76902006">76902006</a><br/><span title="RELATEDTO">?</span><a href="http://snomed.info/id/27836007">27836007</a><br/><span title="RELATEDTO">?</span><a href="http://snomed.info/id/397430003">397430003</a></td><td><span title="EQUIVALENT">~</span>VAC0639</td></tr><tr><td><a href="CodeSystem-ch-vacd-swissmedic-cs.html#ch-vacd-swissmedic-cs-68317">68317</a></td><td>Adacel 0.5 ml</td><td>Adacel 0.5 ml, suspension injectable en seringue préremplie, Sanofi-Aventis (Suisse) SA</td><td><span title="RELATEDTO">?</span><a href="http://snomed.info/id/76902006">76902006</a><br/><span title="RELATEDTO">?</span><a href="http://snomed.info/id/27836007">27836007</a><br/><span title="RELATEDTO">?</span><a href="http://snomed.info/id/397430003">397430003</a></td><td><span title="EQUIVALENT">~</span>VAC0182</td></tr><tr><td><a href="CodeSystem-ch-vacd-swissmedic-cs.html#ch-vacd-swissmedic-cs-68221">68221</a></td><td>MenQuadfi</td><td>MenQuadfi, solution injectable, Sanofi-Aventis (Suisse) SA</td><td><span title="RELATEDTO">?</span><a href="http://snomed.info/id/23511006">23511006</a><br/><span title="RELATEDTO">?</span><a href="http://snomed.info/id/860805006">860805006</a></td><td><span title="EQUIVALENT">~</span>VAC0594</td></tr><tr><td><a href="CodeSystem-ch-vacd-swissmedic-cs.html#ch-vacd-swissmedic-cs-69123">69123</a></td><td>Spikevax Bivalent Original / Omicron 10 mg/ml</td><td>Spikevax Bivalent Original / Omicron 10 mg/ml, Fertigspritze, Moderna Switzerland GmbH</td><td><span title="RELATEDTO">?</span><a href="http://snomed.info/id/840539006">840539006</a></td><td><span title="EQUIVALENT">~</span>VAC1032</td></tr><tr><td><a href="CodeSystem-ch-vacd-swissmedic-cs.html#ch-vacd-swissmedic-cs-69010">69010</a></td><td>Spikevax</td><td>Spikevax, Fertigspritze,	Moderna Switzerland GmbH</td><td><span title="RELATEDTO">?</span><a href="http://snomed.info/id/840539006">840539006</a></td><td><span title="EQUIVALENT">~</span>VAC1031</td></tr><tr><td><a href="CodeSystem-ch-vacd-swissmedic-cs.html#ch-vacd-swissmedic-cs-69047">69047</a></td><td>Comirnaty® Original/Omicron BA.1 15/15 µg pro Dosis</td><td>Comirnaty® Original/Omicron BA.1 15/15 µg pro Dosis, gebrauchsfertige Injektionsdispersion für Personen ab 18 Jahren, Pfizer AG</td><td><span title="RELATEDTO">?</span><a href="http://snomed.info/id/840539006">840539006</a></td><td><span title="EQUIVALENT">~</span>VAC1021</td></tr><tr><td><a href="CodeSystem-ch-vacd-swissmedic-cs.html#ch-vacd-swissmedic-cs-69127">69127</a></td><td>Comirnaty Original/Omicron BA. 4-5 0.225 mg</td><td>Comirnaty Original/Omicron BA. 4-5 0.225 mg, Injektionsdispersion,	Pfizer AG</td><td><span title="RELATEDTO">?</span><a href="http://snomed.info/id/840539006">840539006</a></td><td><span title="EQUIVALENT">~</span>VAC1023</td></tr><tr><td><a href="CodeSystem-ch-vacd-swissmedic-cs.html#ch-vacd-swissmedic-cs-69189">69189</a></td><td>Spikevax Bivalent Original / Omicron BA.4-5</td><td>Spikevax Bivalent Original / Omicron BA.4-5, dispersion for injection,	Moderna Switzerland GmbH</td><td><span title="RELATEDTO">?</span><a href="http://snomed.info/id/840539006">840539006</a></td><td><span title="EQUIVALENT">~</span>VAC1036</td></tr><tr><td><a href="CodeSystem-ch-vacd-swissmedic-cs.html#ch-vacd-swissmedic-cs-69211">69211</a></td><td>Spikevax Bivalent Original / Omicron BA.4-5</td><td>Spikevax Bivalent Original / Omicron BA.4-5, Fertigspritze,	Moderna Switzerland GmbH</td><td><span title="RELATEDTO">?</span><a href="http://snomed.info/id/840539006">840539006</a></td><td><span title="EQUIVALENT">~</span>VAC1036</td></tr><tr><td><a href="CodeSystem-ch-vacd-swissmedic-cs.html#ch-vacd-swissmedic-cs-68752">68752</a></td><td>Vaxneuvance</td><td>Vaxneuvance, Injektionssuspension,	MSD Merck Sharp &amp; Dohme AG</td><td><span title="RELATEDTO">?</span><a href="http://snomed.info/id/16814004">16814004</a></td><td><span title="EQUIVALENT">~</span>VAC0780</td></tr><tr><td><a href="CodeSystem-ch-vacd-swissmedic-cs.html#ch-vacd-swissmedic-cs-69465">69465</a></td><td>Spikevax XBB.1.5 0.10 mg/ml</td><td>Spikevax XBB.1.5 0.10 mg/ml, Dispersion zur Injektion	Moderna Switzerland GmbH</td><td><span title="RELATEDTO">?</span><a href="http://snomed.info/id/840539006">840539006</a></td><td><span title="EQUIVALENT">~</span>VAC1058</td></tr><tr><td><a href="CodeSystem-ch-vacd-swissmedic-cs.html#ch-vacd-swissmedic-cs-69484">69484</a></td><td>Spikevax XBB.1.5 0.10 mg/ml</td><td>Spikevax XBB.1.5 0.10 mg/ml, Dispersion zur Injektion	Moderna Switzerland GmbH</td><td><span title="RELATEDTO">?</span><a href="http://snomed.info/id/840539006">840539006</a></td><td><span title="EQUIVALENT">~</span>VAC1058</td></tr><tr><td><a href="CodeSystem-ch-vacd-swissmedic-cs.html#ch-vacd-swissmedic-cs-69488">69488</a></td><td>Comirnaty Omicron XBB.1.5 (30 Mikrogramm)/dose</td><td>Comirnaty Omicron XBB.1.5 (30 Mikrogramm)/Dosis, Injektionsdispersion	Pfizer AG</td><td><span title="RELATEDTO">?</span><a href="http://snomed.info/id/840539006">840539006</a></td><td><span title="EQUIVALENT">~</span>VAC1051</td></tr><tr><td><a href="CodeSystem-ch-vacd-swissmedic-cs.html#ch-vacd-swissmedic-cs-69310">69310</a></td><td>AREXVY</td><td>AREXVY, Pulver und Suspension zur Herstellung einer Injektionssuspension, GlaxoSmithKline AG</td><td><span title="RELATEDTO">?</span><a href="http://snomed.info/id/55735004">55735004</a></td><td><span title="EQUIVALENT">~</span>VAC1040</td></tr><tr><td><a href="CodeSystem-ch-vacd-swissmedic-cs.html#ch-vacd-swissmedic-cs-69173">69173</a></td><td>Jynneos</td><td>Jynneos</td><td><span title="RELATEDTO">?</span><a href="http://snomed.info/id/359814004">359814004</a><br/><span title="RELATEDTO">?</span><a href="http://snomed.info/id/67924001">67924001</a></td><td><span title="EQUIVALENT">~</span>VAC0966</td></tr><tr><td><a href="CodeSystem-ch-vacd-swissmedic-cs.html#ch-vacd-swissmedic-cs-69222">69222</a></td><td>Prevenar 20</td><td>Prevenar 20, Injektionssuspension in einer Fertigspritze, Pfizer AG</td><td><span title="RELATEDTO">?</span><a href="http://snomed.info/id/16814004">16814004</a></td><td><span title="EQUIVALENT">~</span>VAC0900</td></tr><tr><td><a href="CodeSystem-ch-vacd-swissmedic-cs.html#ch-vacd-swissmedic-cs-69815">69815</a></td><td>Comirnaty Omicron XBB.1.5, 0.042 mg</td><td>Comirnaty Omicron XBB.1.5, 0.042 mg</td><td><span title="RELATEDTO">?</span><a href="http://snomed.info/id/840539006">840539006</a></td><td><span title="EQUIVALENT">~</span>VAC1053</td></tr><tr><td><a href="CodeSystem-ch-vacd-swissmedic-cs.html#ch-vacd-swissmedic-cs-69403">69403</a></td><td>Qdenga 0.5 ml</td><td>Qdenga 0.5 ml, Pulver und Lösungsmittel für eine Injektionslösung, Takeda Pharma AG</td><td><span title="RELATEDTO">?</span><a href="http://snomed.info/id/38362002">38362002</a></td><td><span title="EQUIVALENT">~</span>VAC0644</td></tr><tr><td><a href="CodeSystem-ch-vacd-swissmedic-cs.html#ch-vacd-swissmedic-cs-69913">69913</a></td><td>Comirnaty JN.1 0.042 mg</td><td>Comirnaty JN.1 0.042 mg, Injektionsdispersion in einer Fertigspritze, Pfizer AG</td><td><span title="RELATEDTO">?</span><a href="http://snomed.info/id/840539006">840539006</a></td><td><span title="EQUIVALENT">~</span>VAC1260</td></tr><tr><td><a href="CodeSystem-ch-vacd-swissmedic-cs.html#ch-vacd-swissmedic-cs-69912-01">69912-01</a></td><td>Comirnaty JN.1 30 µg</td><td>Comirnaty JN.1 30 µg, Injektionsdispersion, Pfizer AG</td><td><span title="RELATEDTO">?</span><a href="http://snomed.info/id/840539006">840539006</a></td><td><span title="EQUIVALENT">~</span>VAC1258</td></tr><tr><td><a href="CodeSystem-ch-vacd-swissmedic-cs.html#ch-vacd-swissmedic-cs-69912-02">69912-02</a></td><td>Comirnaty JN.1 10 µg</td><td>Comirnaty JN.1 10 µg, Injektionsdispersion, Pfizer AG</td><td><span title="RELATEDTO">?</span><a href="http://snomed.info/id/840539006">840539006</a></td><td><span title="EQUIVALENT">~</span>VAC1259</td></tr><tr><td><a href="CodeSystem-ch-vacd-swissmedic-cs.html#ch-vacd-swissmedic-cs-69691">69691</a></td><td>Abrysvo</td><td>Abrysvo</td><td><span title="RELATEDTO">?</span><a href="http://snomed.info/id/55735004">55735004</a></td><td><span title="EQUIVALENT">~</span>VAC1047</td></tr><tr><td><a href="CodeSystem-ch-vacd-swissmedic-cs.html#ch-vacd-swissmedic-cs-69788">69788</a></td><td>Spikevax JN.1 (mRNA-1273.167), 0.10mg/ml</td><td>Spikevax JN.1 (mRNA-1273.167), 0.10mg/ml, Dispersion zur Injektion, Moderna Switzerland GmbH</td><td><span title="RELATEDTO">?</span><a href="http://snomed.info/id/840539006">840539006</a></td><td><span title="EQUIVALENT">~</span>VAC1270</td></tr><tr><td><a href="CodeSystem-ch-vacd-swissmedic-cs.html#ch-vacd-swissmedic-cs-70205">70205</a></td><td>Spikevax LP.8.1</td><td>Spikevax LP.8.1, Moderna Switzerland GmbH</td><td><span title="RELATEDTO">?</span><a href="http://snomed.info/id/840539006">840539006</a></td><td><span title="EQUIVALENT">~</span>VAC1500</td></tr><tr><td><a href="CodeSystem-ch-vacd-swissmedic-cs.html#ch-vacd-swissmedic-cs-70400">70400</a></td><td>Comirnaty LP.8.1 10 µg</td><td>Comirnaty LP.8.1 10 μg, Injektionsdispersion, Pfizer AG</td><td><span title="RELATEDTO">?</span><a href="http://snomed.info/id/840539006">840539006</a></td><td><span title="EQUIVALENT">~</span>VAC1468</td></tr><tr><td><a href="CodeSystem-ch-vacd-swissmedic-cs.html#ch-vacd-swissmedic-cs-70403">70403</a></td><td>Comirnaty LP.8.1 30 µg</td><td>Comirnaty LP.8.1 30 Mikrogramm, Injektionsdispersion in einer Fertigspritze, Pfizer AG</td><td><span title="RELATEDTO">?</span><a href="http://snomed.info/id/840539006">840539006</a></td><td><span title="EQUIVALENT">~</span>VAC1466</td></tr><tr><td><a href="CodeSystem-ch-vacd-swissmedic-cs.html#ch-vacd-swissmedic-cs-69863-01">69863-01</a></td><td>Efluelda TIV 0.5 mL</td><td>Efluelda TIV 0.5 mL, suspension injectable en seringue pré-remplie, Sanofi-Aventis (Suisse) SA</td><td><span title="RELATEDTO">?</span><a href="http://snomed.info/id/442438000">442438000</a><br/><span title="RELATEDTO">?</span><a href="http://snomed.info/id/24662006">24662006</a></td><td><span title="EQUIVALENT">~</span>VAC1347</td></tr><tr><td><a href="CodeSystem-ch-vacd-swissmedic-cs.html#ch-vacd-swissmedic-cs-69995-01">69995-01</a></td><td>mResvia Respiratorisches-Synzytial-Virus (RSV) Vakzin 0.10 mg/ml</td><td>mResvia Respiratorisches-Synzytial-Virus (RSV) Vakzin 0.10 mg/ml, Injektionsdispersion, Moderna Switzerland GmbH</td><td><span title="RELATEDTO">?</span><a href="http://snomed.info/id/55735004">55735004</a></td><td><span title="EQUIVALENT">~</span>VAC1262</td></tr><tr><td><a href="CodeSystem-ch-vacd-swissmedic-cs.html#ch-vacd-swissmedic-cs-69781">69781</a></td><td>Capvaxive</td><td>Capvaxive, Injektionslösung in Fertigspritze, MSD Merck Sharp &amp; Dohme AG</td><td><span title="RELATEDTO">?</span><a href="http://snomed.info/id/16814004">16814004</a></td><td><span title="EQUIVALENT">~</span>VAC1254</td></tr><tr><td><a href="CodeSystem-ch-vacd-swissmedic-cs.html#ch-vacd-swissmedic-cs-70042">70042</a></td><td>Fluarix</td><td>Fluarix, Injektionssuspension, GlaxoSmithKline AG</td><td><span title="RELATEDTO">?</span><a href="http://snomed.info/id/719590007">719590007</a></td><td><span title="EQUIVALENT">~</span>VAC0047</td></tr><tr><td><a href="CodeSystem-ch-vacd-swissmedic-cs.html#ch-vacd-swissmedic-cs-69992">69992</a></td><td>Influvac 0.5 ml</td><td>Influvac 0.5 ml, Injektionssuspension in einer Fertigspritze, Viatris Pharma GmbH</td><td><span title="RELATEDTO">?</span><a href="http://snomed.info/id/719590007">719590007</a></td><td/></tr><tr><td><a href="CodeSystem-ch-vacd-swissmedic-cs.html#ch-vacd-swissmedic-cs-70144">70144</a></td><td>Flucelvax</td><td>Flucelvax, Injektionssuspension in einer Fertigspritze, Vifor (International) Inc.</td><td><span title="RELATEDTO">?</span><a href="http://snomed.info/id/719590007">719590007</a></td><td><span title="EQUIVALENT">~</span>VAC0926</td></tr><tr><td><a href="CodeSystem-ch-vacd-swissmedic-cs.html#ch-vacd-swissmedic-cs-70490">70490</a></td><td>Vimkunya</td><td>Vimkunya, Injektionssuspension in einer Fertigspritze, Bavarian Nordic Berna GmbH</td><td><span title="RELATEDTO">?</span><a href="http://snomed.info/id/111864006">111864006</a></td><td><span title="EQUIVALENT">~</span>VAC1267</td></tr></table></li></ul></div>
  </text>
  <url value="http://fhir.ch/ig/ch-vacd/ValueSet/ch-vacd-swissmedic-vaccines-vs"/>
  <version value="3.4.0"/>
  <name value="SwissMedicVaccines"/>
  <title value="CH VACD Swissmedic Authorized Vaccine Codes"/>
  <status value="active"/>
  <experimental value="false"/>
  <date value="2026-06-10T10:00:23+00:00"/>
  <publisher value="HL7 Switzerland"/>
  <contact>
    <name value="HL7 Switzerland"/>
    <telecom>
      <system value="url"/>
      <value value="https://www.hl7.ch/"/>
    </telecom>
  </contact>
  <contact>
    <name value="HL7 Switzerland"/>
    <telecom>
      <system value="url"/>
      <value value="https://www.hl7.ch/"/>
      <use value="work"/>
    </telecom>
  </contact>
  <description value="The list of vaccines available in Switzerland (Swissmedic authorized)."/>
  <jurisdiction>
    <coding>
      <system value="urn:iso:std:iso:3166"/>
      <code value="CH"/>
    </coding>
  </jurisdiction>
  <copyright value="CC0-1.0"/>
  <compose>
    <include>
      <system value="http://fhir.ch/ig/ch-vacd/CodeSystem/ch-vacd-swissmedic-cs"/>
      <concept>
        <code value="683"/>
        <display value="FSME-Immun 0.25 ml Junior"/>
      </concept>
      <concept>
        <code value="450"/>
        <display value="FSME-Immun CC"/>
      </concept>
      <concept>
        <code value="656"/>
        <display value="NeisVac-C"/>
      </concept>
      <concept>
        <code value="627"/>
        <display value="Encepur N"/>
      </concept>
      <concept>
        <code value="628"/>
        <display value="Encepur N Kinder / Enfants"/>
      </concept>
      <concept>
        <code value="572"/>
        <display value="Epaxal"/>
      </concept>
      <concept>
        <code value="544"/>
        <display value="Heprecomb"/>
      </concept>
      <concept>
        <code value="642"/>
        <display value="Heprecomb Kinder"/>
      </concept>
      <concept>
        <code value="614"/>
        <display value="Inflexal V"/>
      </concept>
      <concept>
        <code value="657"/>
        <display value="Menjugate"/>
      </concept>
      <concept>
        <code value="533"/>
        <display value="Moraten"/>
      </concept>
      <concept>
        <code value="555"/>
        <display value="Orochol"/>
      </concept>
      <concept>
        <code value="685"/>
        <display value="Rabipur"/>
      </concept>
      <concept>
        <code value="702"/>
        <display value="Td-pur"/>
      </concept>
      <concept>
        <code value="686"/>
        <display value="Td-Virelon"/>
      </concept>
      <concept>
        <code value="467"/>
        <display value="Vivotif"/>
      </concept>
      <concept>
        <code value="637"/>
        <display value="Boostrix"/>
      </concept>
      <concept>
        <code value="681"/>
        <display value="Boostrix Polio"/>
      </concept>
      <concept>
        <code value="567"/>
        <display value="Ditanrix"/>
      </concept>
      <concept>
        <code value="551"/>
        <display value="Engerix-B 10"/>
      </concept>
      <concept>
        <code value="534"/>
        <display value="Engerix-B 20"/>
      </concept>
      <concept>
        <code value="583"/>
        <display value="Fluarix"/>
      </concept>
      <concept>
        <code value="558"/>
        <display value="Havrix 1440"/>
      </concept>
      <concept>
        <code value="599"/>
        <display value="Havrix 720"/>
      </concept>
      <concept>
        <code value="603"/>
        <display value="Hiberix"/>
      </concept>
      <concept>
        <code value="638"/>
        <display value="Infanrix DTPa-IPV"/>
      </concept>
      <concept>
        <code value="619"/>
        <display value="Infanrix DTPa-IPV+Hib"/>
      </concept>
      <concept>
        <code value="640"/>
        <display value="Infanrix hexa"/>
      </concept>
      <concept>
        <code value="652"/>
        <display value="Mencevax ACWY"/>
      </concept>
      <concept>
        <code value="669"/>
        <display value="Poliorix"/>
      </concept>
      <concept>
        <code value="615"/>
        <display value="Priorix"/>
      </concept>
      <concept>
        <code value="592"/>
        <display value="Twinrix 720/20"/>
      </concept>
      <concept>
        <code value="585"/>
        <display value="Varilrix"/>
      </concept>
      <concept>
        <code value="528"/>
        <display value="Gen H-B-Vax 10"/>
      </concept>
      <concept>
        <code value="545"/>
        <display value="HBVAXPRO 40"/>
      </concept>
      <concept>
        <code value="610"/>
        <display value="Gen H-B-Vax 5"/>
      </concept>
      <concept>
        <code value="663"/>
        <display value="HBVAXPRO 10"/>
      </concept>
      <concept>
        <code value="268"/>
        <display value="MMR-II"/>
      </concept>
      <concept>
        <code value="247"/>
        <display value="Mumpsvax"/>
      </concept>
      <concept>
        <code value="373"/>
        <display value="Mutagrip"/>
      </concept>
      <concept>
        <code value="613"/>
        <display value="Pentavac"/>
      </concept>
      <concept>
        <code value="509"/>
        <display value="Pneumovax-23"/>
      </concept>
      <concept>
        <code value="646"/>
        <display value="Revaxis"/>
      </concept>
      <concept>
        <code value="520"/>
        <display value="Stamaril"/>
      </concept>
      <concept>
        <code value="612"/>
        <display value="Tetravac"/>
      </concept>
      <concept>
        <code value="417"/>
        <display value="Tollwut Impfstoff Mérieux"/>
      </concept>
      <concept>
        <code value="688"/>
        <display value="Varivax"/>
      </concept>
      <concept>
        <code value="485"/>
        <display value="Influvac"/>
      </concept>
      <concept>
        <code value="660"/>
        <display value="Influvac plus"/>
      </concept>
      <concept>
        <code value="654"/>
        <display value="Meningitec"/>
      </concept>
      <concept>
        <code value="643"/>
        <display value="Prevenar-7"/>
      </concept>
      <concept>
        <code value="644"/>
        <display value="Hexavac"/>
      </concept>
      <concept>
        <code value="711"/>
        <display value="DiTe pediatric adsorbed"/>
      </concept>
      <concept>
        <code value="711-01"/>
        <display value="Diphtherie- und Tetanus-Adsorbatimpfstoff für Kinder unter 8 Jahren"/>
      </concept>
      <concept>
        <code value="711-02"/>
        <display value="Diphtherie- und Tetanus-Adsorbatimpfstoff für Erwachsene und Kinder ab 7 Jahren"/>
      </concept>
      <concept>
        <code value="704"/>
        <display value="Dukoral"/>
      </concept>
      <concept>
        <code value="483"/>
        <display value="Rimevax"/>
      </concept>
      <concept>
        <code value="707"/>
        <display value="Tetanol pur"/>
      </concept>
      <concept>
        <code value="57735"/>
        <display value="Gardasil"/>
      </concept>
      <concept>
        <code value="709"/>
        <display value="Zostavax"/>
      </concept>
      <concept>
        <code value="58158"/>
        <display value="Priorix-Tetra"/>
      </concept>
      <concept>
        <code value="696"/>
        <display value="BCG SSI"/>
      </concept>
      <concept>
        <code value="58317"/>
        <display value="Fluad"/>
      </concept>
      <concept>
        <code value="60150"/>
        <display value="Rotarix"/>
      </concept>
      <concept>
        <code value="703"/>
        <display value="MMRVaxPro"/>
      </concept>
      <concept>
        <code value="58506"/>
        <display value="Measles vaccine live"/>
      </concept>
      <concept>
        <code value="59267"/>
        <display value="Agrippal"/>
      </concept>
      <concept>
        <code value="58271"/>
        <display value="Optaflu"/>
      </concept>
      <concept>
        <code value="57814"/>
        <display value="Cervarix"/>
      </concept>
      <concept>
        <code value="60129"/>
        <display value="Prevenar 13"/>
      </concept>
      <concept>
        <code value="59147"/>
        <display value="Ixiaro"/>
      </concept>
      <concept>
        <code value="62502"/>
        <display value="Menveo"/>
      </concept>
      <concept>
        <code value="600"/>
        <display value="DiTe Anatoxal Erwachsene / Adultes"/>
      </concept>
      <concept>
        <code value="690"/>
        <display value="DiTe Anatoxal N Erwachsene / Adultes"/>
      </concept>
      <concept>
        <code value="689"/>
        <display value="Te Anatoxal N"/>
      </concept>
      <concept>
        <code value="62961"/>
        <display value="Fluarix Tetra"/>
      </concept>
      <concept>
        <code value="66037"/>
        <display value="Menjugate liquid"/>
      </concept>
      <concept>
        <code value="699"/>
        <display value="ProQuad"/>
      </concept>
      <concept>
        <code value="65728"/>
        <display value="Gardasil 9 (Durchstechflasche)"/>
      </concept>
      <concept>
        <code value="65387"/>
        <display value="Gardasil 9"/>
      </concept>
      <concept>
        <code value="66940"/>
        <display value="Vaxelis"/>
      </concept>
      <concept>
        <code value="66427"/>
        <display value="VaxigripTetra"/>
      </concept>
      <concept>
        <code value="65730"/>
        <display value="Bexsero"/>
      </concept>
      <concept>
        <code value="68087"/>
        <display value="Influvac Tetra"/>
      </concept>
      <concept>
        <code value="68267"/>
        <display value="Spikevax (COVID-19 Vaccine, Moderna)"/>
      </concept>
      <concept>
        <code value="68225"/>
        <display value="Comirnaty (COVID-19 Vaccine, Pfizer)"/>
      </concept>
      <concept>
        <code value="68235"/>
        <display value="COVID-19 Vaccine Janssen"/>
      </concept>
      <concept>
        <code value="67987"/>
        <display value="Shingrix"/>
      </concept>
      <concept>
        <code value="67482"/>
        <display value="Flucelvax Tetra"/>
      </concept>
      <concept>
        <code value="67704"/>
        <display value="Efluelda 0.7 ml"/>
      </concept>
      <concept>
        <code value="68003"/>
        <display value="Supemtek 0.5 ml"/>
      </concept>
      <concept>
        <code value="66161"/>
        <display value="Foclivia (Durchstechflasche)"/>
      </concept>
      <concept>
        <code value="66156"/>
        <display value="Foclivia (Fertigspritze)"/>
      </concept>
      <concept>
        <code value="68473"/>
        <display value="Nuvaxovid 0.5 ml"/>
      </concept>
      <concept>
        <code value="68358"/>
        <display value="Ervebo"/>
      </concept>
      <concept>
        <code value="68710-01"/>
        <display value="Comirnaty® 30 Mikrogramm/Dosis"/>
      </concept>
      <concept>
        <code value="68710-02"/>
        <display value="Comirnaty® 10 Mikrogramm/Dosis"/>
      </concept>
      <concept>
        <code value="68710-03"/>
        <display value="Comirnaty® 3 Mikrogramm/Dosis"/>
      </concept>
      <concept>
        <code value="68462"/>
        <display value="Fluenz Tetra"/>
      </concept>
      <concept>
        <code value="69009"/>
        <display value="Spikevax Bivalent Original / Omicron"/>
      </concept>
      <concept>
        <code value="68110"/>
        <display value="Adacel-Polio 0.5 ml"/>
      </concept>
      <concept>
        <code value="68317"/>
        <display value="Adacel 0.5 ml"/>
      </concept>
      <concept>
        <code value="68221"/>
        <display value="MenQuadfi"/>
      </concept>
      <concept>
        <code value="69123"/>
        <display value="Spikevax Bivalent Original / Omicron 10 mg/ml"/>
      </concept>
      <concept>
        <code value="69010"/>
        <display value="Spikevax"/>
      </concept>
      <concept>
        <code value="69047"/>
        <display value="Comirnaty® Original/Omicron BA.1 15/15 µg pro Dosis"/>
      </concept>
      <concept>
        <code value="69127"/>
        <display value="Comirnaty Original/Omicron BA. 4-5 0.225 mg"/>
      </concept>
      <concept>
        <code value="69189"/>
        <display value="Spikevax Bivalent Original / Omicron BA.4-5"/>
      </concept>
      <concept>
        <code value="69211"/>
        <display value="Spikevax Bivalent Original / Omicron BA.4-5"/>
      </concept>
      <concept>
        <code value="68752"/>
        <display value="Vaxneuvance"/>
      </concept>
      <concept>
        <code value="69465"/>
        <display value="Spikevax XBB.1.5 0.10 mg/ml"/>
      </concept>
      <concept>
        <code value="69484"/>
        <display value="Spikevax XBB.1.5 0.10 mg/ml"/>
      </concept>
      <concept>
        <code value="69488"/>
        <display value="Comirnaty Omicron XBB.1.5 (30 Mikrogramm)/dose"/>
      </concept>
      <concept>
        <code value="69310"/>
        <display value="AREXVY"/>
      </concept>
      <concept>
        <code value="69173"/>
        <display value="Jynneos"/>
      </concept>
      <concept>
        <code value="69222"/>
        <display value="Prevenar 20"/>
      </concept>
      <concept>
        <code value="69815"/>
        <display value="Comirnaty Omicron XBB.1.5, 0.042 mg"/>
      </concept>
      <concept>
        <code value="69403"/>
        <display value="Qdenga 0.5 ml"/>
      </concept>
      <concept>
        <code value="69913"/>
        <display value="Comirnaty JN.1 0.042 mg"/>
      </concept>
      <concept>
        <code value="69912-01"/>
        <display value="Comirnaty JN.1 30 µg"/>
      </concept>
      <concept>
        <code value="69912-02"/>
        <display value="Comirnaty JN.1 10 µg"/>
      </concept>
      <concept>
        <code value="69691"/>
        <display value="Abrysvo"/>
      </concept>
      <concept>
        <code value="69788"/>
        <display value="Spikevax JN.1 (mRNA-1273.167), 0.10mg/ml"/>
      </concept>
      <concept>
        <code value="70205"/>
        <display value="Spikevax LP.8.1"/>
      </concept>
      <concept>
        <code value="70400"/>
        <display value="Comirnaty LP.8.1 10 µg"/>
      </concept>
      <concept>
        <code value="70403"/>
        <display value="Comirnaty LP.8.1 30 µg"/>
      </concept>
      <concept>
        <code value="69863-01"/>
        <display value="Efluelda TIV 0.5 mL"/>
      </concept>
      <concept>
        <code value="69995-01"/>
        <display value="mResvia Respiratorisches-Synzytial-Virus (RSV) Vakzin 0.10 mg/ml"/>
      </concept>
      <concept>
        <code value="69781"/>
        <display value="Capvaxive"/>
      </concept>
      <concept>
        <code value="70042"/>
        <display value="Fluarix"/>
      </concept>
      <concept>
        <code value="69992"/>
        <display value="Influvac 0.5 ml"/>
      </concept>
      <concept>
        <code value="70144"/>
        <display value="Flucelvax"/>
      </concept>
      <concept>
        <code value="70490"/>
        <display value="Vimkunya"/>
      </concept>
    </include>
  </compose>
</ValueSet>