<?xml version="1.0" encoding="UTF-8"?>

<Bundle xmlns="http://hl7.org/fhir">
  <id value="UC2-Bundle-emr-WalterSchmid"/>
  <meta>
    <lastUpdated value="2026-06-02T08:00:00+02:00"/>
    <profile value="http://fhir.ch/ig/ch-emr/StructureDefinition/ch-emr-bundle"/>
  </meta>
  <language value="de-CH"/>
  <identifier>
    <system value="urn:ietf:rfc:3986"/>
    <value value="urn:uuid:22222222-aaaa-4222-8222-222222222222"/>
  </identifier>
  <type value="document"/>
  <timestamp value="2026-06-02T08:00:00+02:00"/>
  <entry>
    <fullUrl value="http://fhir.ch/ig/emr/Composition/UC2-Composition-emr-WalterSchmid"/>
    <resource>
      <Composition>
        <id value="UC2-Composition-emr-WalterSchmid"/>
        <meta>
          <profile value="http://fhir.ch/ig/ch-emr/StructureDefinition/ch-emr-composition"/>
        </meta>
        <language value="de-CH"/>
        <text>
          <status value="generated"/><div xmlns="http://www.w3.org/1999/xhtml" xml:lang="de-CH" lang="de-CH"><a name="Composition_UC2-Composition-emr-WalterSchmid"> </a><p class="res-header-id"><b>Generated Narrative: Composition UC2-Composition-emr-WalterSchmid</b></p><a name="UC2-Composition-emr-WalterSchmid"> </a><a name="hcUC2-Composition-emr-WalterSchmid"> </a><div style="display: inline-block; background-color: #d9e0e7; padding: 6px; margin: 4px; border: 1px solid #8da1b4; border-radius: 5px; line-height: 60%"><p style="margin-bottom: 0px">Language: de-CH</p><p style="margin-bottom: 0px">Profile: <a href="StructureDefinition-ch-emr-composition.html">CH Emergency Record Composition</a></p></div><p><b>identifier</b>: <a href="http://terminology.hl7.org/7.1.0/NamingSystem-uri.html" title="As defined by RFC 3986 (http://www.ietf.org/rfc/rfc3986.txt)(with many schemes defined in many RFCs). For OIDs and UUIDs, use the URN form (urn:oid:(note: lowercase) and urn:uuid:). See http://www.ietf.org/rfc/rfc3001.txt and http://www.ietf.org/rfc/rfc4122.txt 

This oid is used as an identifier II.root to indicate the the extension is an absolute URI (technically, an IRI). Typically, this is used for OIDs and GUIDs. Note that when this OID is used with OIDs and GUIDs, the II.extension should start with urn:oid or urn:uuid: 

Note that this OID is created to aid with interconversion between CDA and FHIR - FHIR uses urn:ietf:rfc:3986 as equivalent to this OID. URIs as identifiers appear more commonly in FHIR.

This OID may also be used in CD.codeSystem.">Uniform Resource Identifier (URI)</a>/urn:uuid:22222222-aaaa-4222-8222-222222222222</p><p><b>status</b>: Final</p><p><b>type</b>: <span title="Codes:{http://loinc.org 60591-5}">Patient summary Document</span></p><p><b>date</b>: 2026-06-02 08:00:00+0200</p><p><b>author</b>: <a href="PractitionerRole-UC2-PractitionerRole-Hausarzt.html">PractitionerRole Physician</a></p><p><b>title</b>: Elektronischer Notfallpass — Walter Schmid</p><p><b>confidentiality</b>: normal</p></div>
        </text>
        <identifier>
          <system value="urn:ietf:rfc:3986"/>
          <value value="urn:uuid:22222222-aaaa-4222-8222-222222222222"/>
        </identifier>
        <status value="final"/>
        <type>
          <coding>
            <system value="http://loinc.org"/>
            <code value="60591-5"/>
          </coding>
        </type>
        <subject>
          <reference value="Patient/UC2-Patient-WalterSchmid"/>
        </subject>
        <date value="2026-06-02T08:00:00+02:00"/>
        <author>
          <reference value="PractitionerRole/UC2-PractitionerRole-Hausarzt"/>
        </author>
        <title value="Elektronischer Notfallpass — Walter Schmid"/>
        <confidentiality value="N">
          <extension url="http://fhir.ch/ig/ch-core/StructureDefinition/ch-ext-epr-confidentialitycode">
            <valueCodeableConcept>
              <coding>
                <system value="http://snomed.info/sct"/>
                <version value="http://snomed.info/sct/2011000195101"/>
                <code value="17621005"/>
              </coding>
            </valueCodeableConcept>
          </extension>
        </confidentiality>
        <section>
          <title value="Notfallkontakte"/>
          <code>
            <coding>
              <system value="http://loinc.org"/>
              <code value="56864-2"/>
            </coding>
          </code>
          <text>
            <status value="generated"/><div xmlns="http://www.w3.org/1999/xhtml"><ul><li>Spitex Luzern (Pflegedienst): +41 41 555 00 00</li></ul></div>
          </text>
          <entry>
            <reference value="RelatedPerson/UC2-RelatedPerson-Spitex"/>
          </entry>
        </section>
        <section>
          <title value="Behandelnde Gesundheitsfachperson"/>
          <code>
            <coding>
              <system value="http://loinc.org"/>
              <code value="85847-2"/>
            </coding>
          </code>
          <text>
            <status value="generated"/><div xmlns="http://www.w3.org/1999/xhtml"><ul><li>Dr. med. UC2 Hausarzt</li></ul></div>
          </text>
          <entry>
            <reference value="Practitioner/UC2-Practitioner-Hausarzt"/>
          </entry>
          <entry>
            <reference value="PractitionerRole/UC2-PractitionerRole-Hausarzt"/>
          </entry>
        </section>
        <section>
          <title value="Reanimationsstatus"/>
          <code>
            <coding>
              <system value="http://loinc.org"/>
              <code value="100822-6"/>
            </coding>
          </code>
          <text>
            <status value="generated"/><div xmlns="http://www.w3.org/1999/xhtml"><p>Keinen Reanimationsstatus erfasst; siehe Patientenverfügung 2022.</p></div>
          </text>
          <emptyReason>
            <coding>
              <system value="http://terminology.hl7.org/CodeSystem/list-empty-reason"/>
              <code value="unavailable"/>
              <display value="Information not available"/>
            </coding>
          </emptyReason>
        </section>
        <section>
          <title value="Medikation"/>
          <code>
            <coding>
              <system value="http://loinc.org"/>
              <code value="10160-0"/>
            </coding>
          </code>
          <text>
            <status value="generated"/><div xmlns="http://www.w3.org/1999/xhtml"><ul><li>Aspirin cardio 100 mg, 1-0-0-0 — Status nach Schlaganfall</li><li>Atorvastatin 40 mg, 0-0-1-0 — Status nach Schlaganfall (vaskulär bedingt)</li><li>Xigduo XR 1000/5 mg (Metformin/Dapagliflozin), 0-0-2-0 — Diabetes</li><li>Epril 20 mg (Enalapril), 1-0-0-0 — Bluthochdruck</li></ul></div>
          </text>
          <entry>
            <reference value="MedicationStatement/UC2-MedicationStatement-AspirinCardio"/>
          </entry>
          <entry>
            <reference value="MedicationStatement/UC2-MedicationStatement-Atorvastatin"/>
          </entry>
          <entry>
            <reference value="MedicationStatement/UC2-MedicationStatement-XigduoXR"/>
          </entry>
          <entry>
            <reference value="MedicationStatement/UC2-MedicationStatement-Epril"/>
          </entry>
        </section>
        <section>
          <title value="Impfungen"/>
          <code>
            <coding>
              <system value="http://loinc.org"/>
              <code value="11369-6"/>
            </coding>
          </code>
          <text>
            <status value="generated"/><div xmlns="http://www.w3.org/1999/xhtml"><p>Keine Impfungen dokumentiert.</p></div>
          </text>
          <emptyReason>
            <coding>
              <system value="http://terminology.hl7.org/CodeSystem/list-empty-reason"/>
              <code value="unavailable"/>
              <display value="Information not available"/>
            </coding>
          </emptyReason>
        </section>
        <section>
          <title value="Allergien oder Unverträglichkeiten"/>
          <code>
            <coding>
              <system value="http://loinc.org"/>
              <code value="48765-2"/>
            </coding>
          </code>
          <text>
            <status value="generated"/><div xmlns="http://www.w3.org/1999/xhtml"><ul><li>Penicillin — Reaktion: Atemnot</li></ul></div>
          </text>
          <entry>
            <reference value="AllergyIntolerance/UC2-AllergyIntolerance-Penicillin"/>
          </entry>
        </section>
        <section>
          <title value="Risiken für Behandelnde"/>
          <code>
            <coding>
              <system value="http://loinc.org"/>
              <code value="46467-7"/>
            </coding>
          </code>
          <text>
            <status value="generated"/><div xmlns="http://www.w3.org/1999/xhtml"><p>Keine Risikofaktoren bekannt.</p></div>
          </text>
          <emptyReason>
            <coding>
              <system value="http://terminology.hl7.org/CodeSystem/list-empty-reason"/>
              <code value="unavailable"/>
              <display value="Information not available"/>
            </coding>
          </emptyReason>
        </section>
        <section>
          <title value="Probleme und Diagnosen"/>
          <code>
            <coding>
              <system value="http://loinc.org"/>
              <code value="11450-4"/>
            </coding>
          </code>
          <text>
            <status value="generated"/><div xmlns="http://www.w3.org/1999/xhtml"><ul><li>2023 Schlaganfall</li><li>1969 Status nach Splenektomie</li></ul></div>
          </text>
          <entry>
            <reference value="Condition/UC2-Condition-Schlaganfall"/>
          </entry>
          <entry>
            <reference value="Condition/UC2-Condition-Splenektomie"/>
          </entry>
        </section>
        <section>
          <title value="Patientenverfügungen und Ärztliche Notfallanordnung"/>
          <code>
            <coding>
              <system value="http://loinc.org"/>
              <code value="42348-3"/>
            </coding>
          </code>
          <text>
            <status value="generated"/><div xmlns="http://www.w3.org/1999/xhtml"><ul><li>Patientenverfügung 2022 (Hausarzt)</li></ul></div>
          </text>
          <entry>
            <reference value="DocumentReference/UC2-DocumentReference-Patientenverfuegung"/>
          </entry>
        </section>
        <section>
          <title value="Andere Dokumente"/>
          <code>
            <coding>
              <system value="http://loinc.org"/>
              <code value="55108-5"/>
            </coding>
          </code>
          <text>
            <status value="generated"/><div xmlns="http://www.w3.org/1999/xhtml"><p>Keine zusätzlichen Dokumente hinterlegt.</p></div>
          </text>
          <emptyReason>
            <coding>
              <system value="http://terminology.hl7.org/CodeSystem/list-empty-reason"/>
              <code value="unavailable"/>
              <display value="Information not available"/>
            </coding>
          </emptyReason>
        </section>
        <section>
          <title value="Implantate"/>
          <code>
            <coding>
              <system value="http://loinc.org"/>
              <code value="46264-8"/>
            </coding>
          </code>
          <text>
            <status value="generated"/><div xmlns="http://www.w3.org/1999/xhtml"><p>Keine medizinischen Geräte dokumentiert.</p></div>
          </text>
          <emptyReason>
            <coding>
              <system value="http://terminology.hl7.org/CodeSystem/list-empty-reason"/>
              <code value="nilknown"/>
              <display value="Nil Known"/>
            </coding>
          </emptyReason>
        </section>
        <section>
          <title value="Schwangerschaft"/>
          <code>
            <coding>
              <system value="http://loinc.org"/>
              <code value="10162-6"/>
            </coding>
          </code>
          <text>
            <status value="generated"/><div xmlns="http://www.w3.org/1999/xhtml"><p>Nicht zutreffend.</p></div>
          </text>
          <emptyReason>
            <coding>
              <system value="http://terminology.hl7.org/CodeSystem/list-empty-reason"/>
              <code value="notasked"/>
              <display value="Not Asked"/>
            </coding>
          </emptyReason>
        </section>
        <section>
          <title value="Kognitive Beeinträchtigungen"/>
          <code>
            <coding>
              <system value="http://loinc.org"/>
              <code value="66610-7"/>
            </coding>
          </code>
          <text>
            <status value="generated"/><div xmlns="http://www.w3.org/1999/xhtml"><p>Wachheitszustand wechselhaft (akut, fieberbedingt).</p></div>
          </text>
          <emptyReason>
            <coding>
              <system value="http://terminology.hl7.org/CodeSystem/list-empty-reason"/>
              <code value="unavailable"/>
              <display value="Information not available"/>
            </coding>
          </emptyReason>
        </section>
        <section>
          <title value="Physische Beeinträchtigungen"/>
          <code>
            <coding>
              <system value="http://loinc.org"/>
              <code value="96386-8"/>
            </coding>
          </code>
          <text>
            <status value="generated"/><div xmlns="http://www.w3.org/1999/xhtml"><ul><li>Aphasie nach Schlaganfall</li></ul></div>
          </text>
          <entry>
            <reference value="Observation/UC2-PhysicalDisability-Aphasie"/>
          </entry>
        </section>
      </Composition>
    </resource>
  </entry>
  <entry>
    <fullUrl value="http://fhir.ch/ig/emr/Patient/UC2-Patient-WalterSchmid"/>
    <resource>
      <Patient>
        <id value="UC2-Patient-WalterSchmid"/>
        <meta>
          <profile value="http://fhir.ch/ig/ch-ips/StructureDefinition/ch-ips-patient"/>
        </meta>
        <text>
          <status value="generated"/><div xmlns="http://www.w3.org/1999/xhtml"><a name="Patient_UC2-Patient-WalterSchmid"> </a><p class="res-header-id"><b>Generated Narrative: Patient UC2-Patient-WalterSchmid</b></p><a name="UC2-Patient-WalterSchmid"> </a><a name="hcUC2-Patient-WalterSchmid"> </a><div style="display: inline-block; background-color: #d9e0e7; padding: 6px; margin: 4px; border: 1px solid #8da1b4; border-radius: 5px; line-height: 60%"><p style="margin-bottom: 0px"/><p style="margin-bottom: 0px">Profile: <a href="http://fhir.ch/ig/ch-ips/2.0.0/StructureDefinition-ch-ips-patient.html">CH IPS Patient</a></p></div><p style="border: 1px #661aff solid; background-color: #e6e6ff; padding: 10px;">Walter Schmid (official) Male, DoB: 1947-04-12 ( urn:oid:2.16.756.5.30.1.123.100.1.1.1#InsuranceCardNumber#80756012222222222222)</p><hr/><table class="grid"><tr><td style="background-color: #f3f5da" title="Ways to contact the Patient">Contact Detail</td><td colspan="3">Seestrasse 22 Luzern 6003 CH </td></tr><tr><td style="background-color: #f3f5da" title="Language spoken">Language:</td><td colspan="3"><span title="Codes:{urn:ietf:bcp:47 de}">German</span> (preferred)</td></tr></table></div>
        </text>
        <identifier>
          <system value="urn:oid:2.16.756.5.30.1.123.100.1.1.1"/>
          <value value="80756012222222222222"/>
        </identifier>
        <name>
          <use value="official"/>
          <family value="Schmid"/>
          <given value="Walter"/>
        </name>
        <gender value="male"/>
        <birthDate value="1947-04-12"/>
        <address>
          <line value="Seestrasse 22"/>
          <city value="Luzern"/>
          <postalCode value="6003"/>
          <country value="CH"/>
        </address>
        <communication>
          <language>
            <coding>
              <system value="urn:ietf:bcp:47"/>
              <code value="de"/>
            </coding>
          </language>
          <preferred value="true"/>
        </communication>
      </Patient>
    </resource>
  </entry>
  <entry>
    <fullUrl value="http://fhir.ch/ig/emr/RelatedPerson/UC2-RelatedPerson-Spitex"/>
    <resource>
      <RelatedPerson>
        <id value="UC2-RelatedPerson-Spitex"/>
        <meta>
          <profile value="http://fhir.ch/ig/ch-emr/StructureDefinition/ch-emr-relatedperson"/>
        </meta>
        <text>
          <status value="generated"/><div xmlns="http://www.w3.org/1999/xhtml"><a name="RelatedPerson_UC2-RelatedPerson-Spitex"> </a><p class="res-header-id"><b>Generated Narrative: RelatedPerson UC2-RelatedPerson-Spitex</b></p><a name="UC2-RelatedPerson-Spitex"> </a><a name="hcUC2-RelatedPerson-Spitex"> </a><div style="display: inline-block; background-color: #d9e0e7; padding: 6px; margin: 4px; border: 1px solid #8da1b4; border-radius: 5px; line-height: 60%"><p style="margin-bottom: 0px"/><p style="margin-bottom: 0px">Profile: <a href="StructureDefinition-ch-emr-relatedperson.html">CH Emergency Record RelatedPerson</a></p></div><p><b>active</b>: true</p><p><b>patient</b>: <a href="Patient-UC2-Patient-WalterSchmid.html">Walter Schmid (official) Male, DoB: 1947-04-12 ( urn:oid:2.16.756.5.30.1.123.100.1.1.1#InsuranceCardNumber#80756012222222222222)</a></p><p><b>relationship</b>: <span title="Codes:">Spitex (Pflegedienst)</span></p><p><b>name</b>: Spitex Luzern (Pflegedienst)(Anonymous)</p><p><b>telecom</b>: <a href="tel:+41415550000">+41 41 555 00 00</a></p><h3>Communications</h3><table class="grid"><tr><td style="display: none">-</td><td><b>Language</b></td><td><b>Preferred</b></td></tr><tr><td style="display: none">*</td><td><span title="Codes:{urn:ietf:bcp:47 de}">German</span></td><td>true</td></tr></table></div>
        </text>
        <active value="true"/>
        <patient>
          <reference value="Patient/UC2-Patient-WalterSchmid"/>
        </patient>
        <relationship>
          <text value="Spitex (Pflegedienst)"/>
        </relationship>
        <name>
          <use value="anonymous"/>
          <text value="Spitex Luzern (Pflegedienst)"/>
        </name>
        <telecom>
          <system value="phone"/>
          <value value="+41 41 555 00 00"/>
          <use value="work"/>
          <rank value="1"/>
        </telecom>
        <communication>
          <language>
            <coding>
              <system value="urn:ietf:bcp:47"/>
              <code value="de"/>
            </coding>
          </language>
          <preferred value="true"/>
        </communication>
      </RelatedPerson>
    </resource>
  </entry>
  <entry>
    <fullUrl value="http://fhir.ch/ig/emr/Practitioner/UC2-Practitioner-Hausarzt"/>
    <resource>
      <Practitioner>
        <id value="UC2-Practitioner-Hausarzt"/>
        <meta>
          <profile value="http://fhir.ch/ig/ch-ips/StructureDefinition/ch-ips-practitioner"/>
        </meta>
        <language value="de-CH"/>
        <text>
          <status value="generated"/><div xmlns="http://www.w3.org/1999/xhtml" xml:lang="de-CH" lang="de-CH"><a name="Practitioner_UC2-Practitioner-Hausarzt"> </a><p class="res-header-id"><b>Generated Narrative: Practitioner UC2-Practitioner-Hausarzt</b></p><a name="UC2-Practitioner-Hausarzt"> </a><a name="hcUC2-Practitioner-Hausarzt"> </a><div style="display: inline-block; background-color: #d9e0e7; padding: 6px; margin: 4px; border: 1px solid #8da1b4; border-radius: 5px; line-height: 60%"><p style="margin-bottom: 0px">Language: de-CH</p><p style="margin-bottom: 0px">Profile: <a href="http://fhir.ch/ig/ch-ips/2.0.0/StructureDefinition-ch-ips-practitioner.html">CH IPS Practitioner</a></p></div><p><b>identifier</b>: <a href="http://fhir.ch/ig/ch-term/3.3.0/NamingSystem-gln.html" title="Each healthcare partner (natural or legal person) is referenced with a unique code of type GLN (former name: EAN code) of the [GS1](https://www.gs1.ch/de/home) system, see [refdata](https://www.refdata.ch/).">GLN</a>/7601000000033</p><p><b>name</b>: UC2 Hausarzt (Official)</p><h3>Qualifications</h3><table class="grid"><tr><td style="display: none">-</td><td><b>Code</b></td></tr><tr><td style="display: none">*</td><td><span title="Codes:{http://snomed.info/sct 309343006}">Arzt</span></td></tr></table></div>
        </text>
        <identifier>
          <system value="urn:oid:2.51.1.3"/>
          <value value="7601000000033"/>
        </identifier>
        <name>
          <use value="official"/>
          <family value="Hausarzt"/>
          <given value="UC2"/>
          <prefix value="Dr. med."/>
        </name>
        <qualification>
          <code>
            <coding>
              <system value="http://snomed.info/sct"/>
              <version value="http://snomed.info/sct/2011000195101"/>
              <code value="309343006"/>
            </coding>
            <text value="Arzt"/>
          </code>
        </qualification>
      </Practitioner>
    </resource>
  </entry>
  <entry>
    <fullUrl value="http://fhir.ch/ig/emr/PractitionerRole/UC2-PractitionerRole-Hausarzt"/>
    <resource>
      <PractitionerRole>
        <id value="UC2-PractitionerRole-Hausarzt"/>
        <meta>
          <profile value="http://fhir.ch/ig/ch-ips/StructureDefinition/ch-ips-practitionerrole"/>
        </meta>
        <text>
          <status value="generated"/><div xmlns="http://www.w3.org/1999/xhtml"><a name="PractitionerRole_UC2-PractitionerRole-Hausarzt"> </a><p class="res-header-id"><b>Generated Narrative: PractitionerRole UC2-PractitionerRole-Hausarzt</b></p><a name="UC2-PractitionerRole-Hausarzt"> </a><a name="hcUC2-PractitionerRole-Hausarzt"> </a><div style="display: inline-block; background-color: #d9e0e7; padding: 6px; margin: 4px; border: 1px solid #8da1b4; border-radius: 5px; line-height: 60%"><p style="margin-bottom: 0px"/><p style="margin-bottom: 0px">Profile: <a href="http://fhir.ch/ig/ch-ips/2.0.0/StructureDefinition-ch-ips-practitionerrole.html">CH IPS PractitionerRole</a></p></div><p><b>active</b>: true</p><p><b>practitioner</b>: <a href="Practitioner-UC2-Practitioner-Hausarzt.html">Practitioner UC2 Hausarzt (official)</a></p><p><b>organization</b>: <a href="Organization-UC2-Organization-Hausarztpraxis.html">Organization Hausarztpraxis UC2</a></p><p><b>code</b>: <span title="Codes:{http://snomed.info/sct 309343006}">Arzt</span></p><p><b>specialty</b>: <span title="Codes:{http://snomed.info/sct 419772000}">Allgemeine Innere Medizin</span></p></div>
        </text>
        <active value="true"/>
        <practitioner>
          <reference value="Practitioner/UC2-Practitioner-Hausarzt"/>
        </practitioner>
        <organization>
          <reference value="Organization/UC2-Organization-Hausarztpraxis"/>
        </organization>
        <code>
          <coding>
            <system value="http://snomed.info/sct"/>
            <version value="http://snomed.info/sct/2011000195101"/>
            <code value="309343006"/>
          </coding>
          <text value="Arzt"/>
        </code>
        <specialty>
          <coding>
            <system value="http://snomed.info/sct"/>
            <version value="http://snomed.info/sct/2011000195101"/>
            <code value="419772000"/>
          </coding>
          <text value="Allgemeine Innere Medizin"/>
        </specialty>
      </PractitionerRole>
    </resource>
  </entry>
  <entry>
    <fullUrl value="http://fhir.ch/ig/emr/Organization/UC2-Organization-Hausarztpraxis"/>
    <resource>
      <Organization>
        <id value="UC2-Organization-Hausarztpraxis"/>
        <meta>
          <profile value="http://fhir.ch/ig/ch-ips/StructureDefinition/ch-ips-organization"/>
        </meta>
        <text>
          <status value="generated"/><div xmlns="http://www.w3.org/1999/xhtml"><a name="Organization_UC2-Organization-Hausarztpraxis"> </a><p class="res-header-id"><b>Generated Narrative: Organization UC2-Organization-Hausarztpraxis</b></p><a name="UC2-Organization-Hausarztpraxis"> </a><a name="hcUC2-Organization-Hausarztpraxis"> </a><div style="display: inline-block; background-color: #d9e0e7; padding: 6px; margin: 4px; border: 1px solid #8da1b4; border-radius: 5px; line-height: 60%"><p style="margin-bottom: 0px"/><p style="margin-bottom: 0px">Profile: <a href="http://fhir.ch/ig/ch-ips/2.0.0/StructureDefinition-ch-ips-organization.html">CH IPS Organization</a></p></div><p><b>identifier</b>: <a href="http://fhir.ch/ig/ch-term/3.3.0/NamingSystem-gln.html" title="Each healthcare partner (natural or legal person) is referenced with a unique code of type GLN (former name: EAN code) of the [GS1](https://www.gs1.ch/de/home) system, see [refdata](https://www.refdata.ch/).">GLN</a>/7601000000040</p><p><b>active</b>: true</p><p><b>type</b>: <span title="Codes:{http://snomed.info/sct 394802001}">Allgemeine Innere Medizin</span></p><p><b>name</b>: Hausarztpraxis UC2</p></div>
        </text>
        <identifier>
          <system value="urn:oid:2.51.1.3"/>
          <value value="7601000000040"/>
        </identifier>
        <active value="true"/>
        <type>
          <coding>
            <system value="http://snomed.info/sct"/>
            <version value="http://snomed.info/sct/2011000195101"/>
            <code value="394802001"/>
          </coding>
          <text value="Allgemeine Innere Medizin"/>
        </type>
        <name value="Hausarztpraxis UC2"/>
      </Organization>
    </resource>
  </entry>
  <entry>
    <fullUrl value="http://fhir.ch/ig/emr/Condition/UC2-Condition-Schlaganfall"/>
    <resource>
      <Condition>
        <id value="UC2-Condition-Schlaganfall"/>
        <meta>
          <profile value="http://fhir.ch/ig/ch-ips/StructureDefinition/ch-ips-condition"/>
        </meta>
        <text>
          <status value="generated"/><div xmlns="http://www.w3.org/1999/xhtml"><a name="Condition_UC2-Condition-Schlaganfall"> </a><p class="res-header-id"><b>Generated Narrative: Condition UC2-Condition-Schlaganfall</b></p><a name="UC2-Condition-Schlaganfall"> </a><a name="hcUC2-Condition-Schlaganfall"> </a><div style="display: inline-block; background-color: #d9e0e7; padding: 6px; margin: 4px; border: 1px solid #8da1b4; border-radius: 5px; line-height: 60%"><p style="margin-bottom: 0px"/><p style="margin-bottom: 0px">Profile: <a href="http://fhir.ch/ig/ch-ips/2.0.0/StructureDefinition-ch-ips-condition.html">CH IPS Condition</a></p></div><p><b>clinicalStatus</b>: <span title="Codes:{http://terminology.hl7.org/CodeSystem/condition-clinical active}">Active</span></p><p><b>verificationStatus</b>: <span title="Codes:{http://terminology.hl7.org/CodeSystem/condition-ver-status confirmed}">Confirmed</span></p><p><b>category</b>: <span title="Codes:{http://terminology.hl7.org/CodeSystem/condition-category problem-list-item}">Problem List Item</span></p><p><b>code</b>: <span title="Codes:{http://snomed.info/sct 230690007}">CVA - Cerebrovascular accident</span></p><p><b>subject</b>: <a href="Patient-UC2-Patient-WalterSchmid.html">Walter Schmid (official) Male, DoB: 1947-04-12 ( urn:oid:2.16.756.5.30.1.123.100.1.1.1#InsuranceCardNumber#80756012222222222222)</a></p><p><b>onset</b>: 2023</p><p><b>recordedDate</b>: 2023-01-01</p><p><b>recorder</b>: <a href="Practitioner-UC2-Practitioner-Hausarzt.html">Practitioner UC2 Hausarzt (official)</a></p></div>
        </text>
        <clinicalStatus>
          <coding>
            <system value="http://terminology.hl7.org/CodeSystem/condition-clinical"/>
            <code value="active"/>
          </coding>
        </clinicalStatus>
        <verificationStatus>
          <coding>
            <system value="http://terminology.hl7.org/CodeSystem/condition-ver-status"/>
            <code value="confirmed"/>
          </coding>
        </verificationStatus>
        <category>
          <coding>
            <system value="http://terminology.hl7.org/CodeSystem/condition-category"/>
            <code value="problem-list-item"/>
          </coding>
        </category>
        <code>
          <coding>
            <system value="http://snomed.info/sct"/>
            <version value="http://snomed.info/sct/2011000195101"/>
            <code value="230690007"/>
          </coding>
        </code>
        <subject>
          <reference value="Patient/UC2-Patient-WalterSchmid"/>
        </subject>
        <onsetDateTime value="2023"/>
        <recordedDate value="2023-01-01"/>
        <recorder>
          <reference value="Practitioner/UC2-Practitioner-Hausarzt"/>
        </recorder>
      </Condition>
    </resource>
  </entry>
  <entry>
    <fullUrl value="http://fhir.ch/ig/emr/Condition/UC2-Condition-Splenektomie"/>
    <resource>
      <Condition>
        <id value="UC2-Condition-Splenektomie"/>
        <meta>
          <profile value="http://fhir.ch/ig/ch-ips/StructureDefinition/ch-ips-condition"/>
        </meta>
        <text>
          <status value="generated"/><div xmlns="http://www.w3.org/1999/xhtml"><a name="Condition_UC2-Condition-Splenektomie"> </a><p class="res-header-id"><b>Generated Narrative: Condition UC2-Condition-Splenektomie</b></p><a name="UC2-Condition-Splenektomie"> </a><a name="hcUC2-Condition-Splenektomie"> </a><div style="display: inline-block; background-color: #d9e0e7; padding: 6px; margin: 4px; border: 1px solid #8da1b4; border-radius: 5px; line-height: 60%"><p style="margin-bottom: 0px"/><p style="margin-bottom: 0px">Profile: <a href="http://fhir.ch/ig/ch-ips/2.0.0/StructureDefinition-ch-ips-condition.html">CH IPS Condition</a></p></div><p><b>clinicalStatus</b>: <span title="Codes:{http://terminology.hl7.org/CodeSystem/condition-clinical active}">Active</span></p><p><b>verificationStatus</b>: <span title="Codes:{http://terminology.hl7.org/CodeSystem/condition-ver-status confirmed}">Confirmed</span></p><p><b>category</b>: <span title="Codes:{http://terminology.hl7.org/CodeSystem/condition-category problem-list-item}">Problem List Item</span></p><p><b>code</b>: <span title="Codes:">Status nach Splenektomie (1969)</span></p><p><b>subject</b>: <a href="Patient-UC2-Patient-WalterSchmid.html">Walter Schmid (official) Male, DoB: 1947-04-12 ( urn:oid:2.16.756.5.30.1.123.100.1.1.1#InsuranceCardNumber#80756012222222222222)</a></p><p><b>onset</b>: 1969</p><p><b>recordedDate</b>: 1969-01-01</p></div>
        </text>
        <clinicalStatus>
          <coding>
            <system value="http://terminology.hl7.org/CodeSystem/condition-clinical"/>
            <code value="active"/>
          </coding>
        </clinicalStatus>
        <verificationStatus>
          <coding>
            <system value="http://terminology.hl7.org/CodeSystem/condition-ver-status"/>
            <code value="confirmed"/>
          </coding>
        </verificationStatus>
        <category>
          <coding>
            <system value="http://terminology.hl7.org/CodeSystem/condition-category"/>
            <code value="problem-list-item"/>
          </coding>
        </category>
        <code>
          <text value="Status nach Splenektomie (1969)"/>
        </code>
        <subject>
          <reference value="Patient/UC2-Patient-WalterSchmid"/>
        </subject>
        <onsetDateTime value="1969"/>
        <recordedDate value="1969-01-01"/>
      </Condition>
    </resource>
  </entry>
  <entry>
    <fullUrl value="http://fhir.ch/ig/emr/Medication/UC2-Medication-AspirinCardio"/>
    <resource>
      <Medication>
        <id value="UC2-Medication-AspirinCardio"/>
        <meta>
          <profile value="http://fhir.ch/ig/ch-ips/StructureDefinition/ch-ips-medication"/>
        </meta>
        <text>
          <status value="generated"/><div xmlns="http://www.w3.org/1999/xhtml"><a name="Medication_UC2-Medication-AspirinCardio"> </a><p class="res-header-id"><b>Generated Narrative: Medication UC2-Medication-AspirinCardio</b></p><a name="UC2-Medication-AspirinCardio"> </a><a name="hcUC2-Medication-AspirinCardio"> </a><div style="display: inline-block; background-color: #d9e0e7; padding: 6px; margin: 4px; border: 1px solid #8da1b4; border-radius: 5px; line-height: 60%"><p style="margin-bottom: 0px"/><p style="margin-bottom: 0px">Profile: <a href="http://fhir.ch/ig/ch-ips/2.0.0/StructureDefinition-ch-ips-medication.html">CH IPS Medication</a></p></div><p><b>code</b>: <span title="Codes:{urn:oid:2.51.1.1 7680517950680}, {http://www.whocc.no/atc B01AC06}">Aspirin Cardio 100 mg (Acetylsalicylsäure)</span></p><p><b>form</b>: <span title="Codes:{urn:oid:0.4.0.127.0.16.1.1.2.1 10219000}">Tablette</span></p><p><b>amount</b>: 28 Tablette<span style="background: LightGoldenRodYellow"> (Details: SNOMED CT  code732936001 = '732936001')</span>/1 Packung<span style="background: LightGoldenRodYellow"> (Details: SNOMED CT  code1681000175101 = '1681000175101')</span></p></div>
        </text>
        <code>
          <coding>
            <system value="urn:oid:2.51.1.1"/>
            <code value="7680517950680"/>
            <display value="ASPIRIN CARDIO Filmtabl 100 mg 28 Stk"/>
          </coding>
          <coding>
            <system value="http://www.whocc.no/atc"/>
            <code value="B01AC06"/>
            <display value="acetylsalicylic acid"/>
          </coding>
          <text value="Aspirin Cardio 100 mg (Acetylsalicylsäure)"/>
        </code>
        <form>
          <coding>
            <system value="urn:oid:0.4.0.127.0.16.1.1.2.1"/>
            <code value="10219000"/>
          </coding>
          <text value="Tablette"/>
        </form>
        <amount>
          <numerator>
            <value value="28"/>
            <unit value="Tablette"/>
            <system value="http://snomed.info/sct|http://snomed.info/sct/2011000195101"/>
            <code value="732936001"/>
          </numerator>
          <denominator>
            <value value="1"/>
            <unit value="Packung"/>
            <system value="http://snomed.info/sct|http://snomed.info/sct/2011000195101"/>
            <code value="1681000175101"/>
          </denominator>
        </amount>
      </Medication>
    </resource>
  </entry>
  <entry>
    <fullUrl value="http://fhir.ch/ig/emr/MedicationStatement/UC2-MedicationStatement-AspirinCardio"/>
    <resource>
      <MedicationStatement>
        <id value="UC2-MedicationStatement-AspirinCardio"/>
        <meta>
          <profile value="http://fhir.ch/ig/ch-emr/StructureDefinition/ch-emr-medicationstatement"/>
        </meta>
        <text>
          <status value="generated"/><div xmlns="http://www.w3.org/1999/xhtml"><a name="MedicationStatement_UC2-MedicationStatement-AspirinCardio"> </a><p class="res-header-id"><b>Generated Narrative: MedicationStatement UC2-MedicationStatement-AspirinCardio</b></p><a name="UC2-MedicationStatement-AspirinCardio"> </a><a name="hcUC2-MedicationStatement-AspirinCardio"> </a><div style="display: inline-block; background-color: #d9e0e7; padding: 6px; margin: 4px; border: 1px solid #8da1b4; border-radius: 5px; line-height: 60%"><p style="margin-bottom: 0px"/><p style="margin-bottom: 0px">Profile: <a href="StructureDefinition-ch-emr-medicationstatement.html">CH Emergency Record Medication Statement</a></p></div><p><b>status</b>: Active</p><p><b>medication</b>: <a href="Medication-UC2-Medication-AspirinCardio.html">Medication ASPIRIN CARDIO Filmtabl 100 mg 28 Stk</a></p><p><b>subject</b>: <a href="Patient-UC2-Patient-WalterSchmid.html">Walter Schmid (official) Male, DoB: 1947-04-12 ( urn:oid:2.16.756.5.30.1.123.100.1.1.1#InsuranceCardNumber#80756012222222222222)</a></p><p><b>effective</b>: 2023-02-01 --&gt; (ongoing)</p><p><b>reasonReference</b>: <a href="Condition-UC2-Condition-Schlaganfall.html">Condition CVA - Cerebrovascular accident</a></p><blockquote><p><b>dosage</b></p><p><b>sequence</b>: 1</p><p><b>timing</b>: Morning, Once</p><p><b>route</b>: <span title="Codes:{urn:oid:0.4.0.127.0.16.1.1.2.1 20053000}">zum Einnehmen</span></p><h3>DoseAndRates</h3><table class="grid"><tr><td style="display: none">-</td><td><b>Dose[x]</b></td></tr><tr><td style="display: none">*</td><td>1 Tablette<span style="background: LightGoldenRodYellow"> (Details: SNOMED CT  code732936001 = '732936001')</span></td></tr></table></blockquote></div>
        </text>
        <status value="active"/>
        <medicationReference>
          <reference value="Medication/UC2-Medication-AspirinCardio"/>
        </medicationReference>
        <subject>
          <reference value="Patient/UC2-Patient-WalterSchmid"/>
        </subject>
        <effectivePeriod>
          <start value="2023-02-01"/>
        </effectivePeriod>
        <reasonReference>
          <reference value="Condition/UC2-Condition-Schlaganfall"/>
        </reasonReference>
        <dosage>
          <sequence value="1"/>
          <timing>
            <repeat>
              <when value="MORN"/>
            </repeat>
          </timing>
          <route>
            <coding>
              <system value="urn:oid:0.4.0.127.0.16.1.1.2.1"/>
              <code value="20053000"/>
            </coding>
            <text value="zum Einnehmen"/>
          </route>
          <doseAndRate>
            <doseQuantity>
              <value value="1"/>
              <unit value="Tablette"/>
              <system value="http://snomed.info/sct|http://snomed.info/sct/2011000195101"/>
              <code value="732936001"/>
            </doseQuantity>
          </doseAndRate>
        </dosage>
      </MedicationStatement>
    </resource>
  </entry>
  <entry>
    <fullUrl value="http://fhir.ch/ig/emr/Medication/UC2-Medication-Atorvastatin"/>
    <resource>
      <Medication>
        <id value="UC2-Medication-Atorvastatin"/>
        <meta>
          <profile value="http://fhir.ch/ig/ch-ips/StructureDefinition/ch-ips-medication"/>
        </meta>
        <text>
          <status value="generated"/><div xmlns="http://www.w3.org/1999/xhtml"><a name="Medication_UC2-Medication-Atorvastatin"> </a><p class="res-header-id"><b>Generated Narrative: Medication UC2-Medication-Atorvastatin</b></p><a name="UC2-Medication-Atorvastatin"> </a><a name="hcUC2-Medication-Atorvastatin"> </a><div style="display: inline-block; background-color: #d9e0e7; padding: 6px; margin: 4px; border: 1px solid #8da1b4; border-radius: 5px; line-height: 60%"><p style="margin-bottom: 0px"/><p style="margin-bottom: 0px">Profile: <a href="http://fhir.ch/ig/ch-ips/2.0.0/StructureDefinition-ch-ips-medication.html">CH IPS Medication</a></p></div><p><b>code</b>: <span title="Codes:{urn:oid:2.51.1.1 7680540850605}, {http://www.whocc.no/atc C10AA05}">Sortis 40 mg (Atorvastatin)</span></p><p><b>form</b>: <span title="Codes:{urn:oid:0.4.0.127.0.16.1.1.2.1 10219000}">Tablette</span></p><p><b>amount</b>: 30 Tablette<span style="background: LightGoldenRodYellow"> (Details: SNOMED CT  code732936001 = '732936001')</span>/1 Packung<span style="background: LightGoldenRodYellow"> (Details: SNOMED CT  code1681000175101 = '1681000175101')</span></p></div>
        </text>
        <code>
          <coding>
            <system value="urn:oid:2.51.1.1"/>
            <code value="7680540850605"/>
            <display value="SORTIS Filmtabl 40 mg 30 Stk"/>
          </coding>
          <coding>
            <system value="http://www.whocc.no/atc"/>
            <code value="C10AA05"/>
            <display value="atorvastatin"/>
          </coding>
          <text value="Sortis 40 mg (Atorvastatin)"/>
        </code>
        <form>
          <coding>
            <system value="urn:oid:0.4.0.127.0.16.1.1.2.1"/>
            <code value="10219000"/>
          </coding>
          <text value="Tablette"/>
        </form>
        <amount>
          <numerator>
            <value value="30"/>
            <unit value="Tablette"/>
            <system value="http://snomed.info/sct|http://snomed.info/sct/2011000195101"/>
            <code value="732936001"/>
          </numerator>
          <denominator>
            <value value="1"/>
            <unit value="Packung"/>
            <system value="http://snomed.info/sct|http://snomed.info/sct/2011000195101"/>
            <code value="1681000175101"/>
          </denominator>
        </amount>
      </Medication>
    </resource>
  </entry>
  <entry>
    <fullUrl value="http://fhir.ch/ig/emr/MedicationStatement/UC2-MedicationStatement-Atorvastatin"/>
    <resource>
      <MedicationStatement>
        <id value="UC2-MedicationStatement-Atorvastatin"/>
        <meta>
          <profile value="http://fhir.ch/ig/ch-emr/StructureDefinition/ch-emr-medicationstatement"/>
        </meta>
        <text>
          <status value="generated"/><div xmlns="http://www.w3.org/1999/xhtml"><a name="MedicationStatement_UC2-MedicationStatement-Atorvastatin"> </a><p class="res-header-id"><b>Generated Narrative: MedicationStatement UC2-MedicationStatement-Atorvastatin</b></p><a name="UC2-MedicationStatement-Atorvastatin"> </a><a name="hcUC2-MedicationStatement-Atorvastatin"> </a><div style="display: inline-block; background-color: #d9e0e7; padding: 6px; margin: 4px; border: 1px solid #8da1b4; border-radius: 5px; line-height: 60%"><p style="margin-bottom: 0px"/><p style="margin-bottom: 0px">Profile: <a href="StructureDefinition-ch-emr-medicationstatement.html">CH Emergency Record Medication Statement</a></p></div><p><b>status</b>: Active</p><p><b>medication</b>: <a href="Medication-UC2-Medication-Atorvastatin.html">Medication SORTIS Filmtabl 40 mg 30 Stk</a></p><p><b>subject</b>: <a href="Patient-UC2-Patient-WalterSchmid.html">Walter Schmid (official) Male, DoB: 1947-04-12 ( urn:oid:2.16.756.5.30.1.123.100.1.1.1#InsuranceCardNumber#80756012222222222222)</a></p><p><b>effective</b>: 2023-02-01 --&gt; (ongoing)</p><p><b>reasonReference</b>: <a href="Condition-UC2-Condition-Schlaganfall.html">Condition CVA - Cerebrovascular accident</a></p><blockquote><p><b>dosage</b></p><p><b>sequence</b>: 1</p><p><b>timing</b>: Evening, Once</p><p><b>route</b>: <span title="Codes:{urn:oid:0.4.0.127.0.16.1.1.2.1 20053000}">zum Einnehmen</span></p><h3>DoseAndRates</h3><table class="grid"><tr><td style="display: none">-</td><td><b>Dose[x]</b></td></tr><tr><td style="display: none">*</td><td>1 Tablette<span style="background: LightGoldenRodYellow"> (Details: SNOMED CT  code732936001 = '732936001')</span></td></tr></table></blockquote></div>
        </text>
        <status value="active"/>
        <medicationReference>
          <reference value="Medication/UC2-Medication-Atorvastatin"/>
        </medicationReference>
        <subject>
          <reference value="Patient/UC2-Patient-WalterSchmid"/>
        </subject>
        <effectivePeriod>
          <start value="2023-02-01"/>
        </effectivePeriod>
        <reasonReference>
          <reference value="Condition/UC2-Condition-Schlaganfall"/>
        </reasonReference>
        <dosage>
          <sequence value="1"/>
          <timing>
            <repeat>
              <when value="EVE"/>
            </repeat>
          </timing>
          <route>
            <coding>
              <system value="urn:oid:0.4.0.127.0.16.1.1.2.1"/>
              <code value="20053000"/>
            </coding>
            <text value="zum Einnehmen"/>
          </route>
          <doseAndRate>
            <doseQuantity>
              <value value="1"/>
              <unit value="Tablette"/>
              <system value="http://snomed.info/sct|http://snomed.info/sct/2011000195101"/>
              <code value="732936001"/>
            </doseQuantity>
          </doseAndRate>
        </dosage>
      </MedicationStatement>
    </resource>
  </entry>
  <entry>
    <fullUrl value="http://fhir.ch/ig/emr/Medication/UC2-Medication-XigduoXR"/>
    <resource>
      <Medication>
        <id value="UC2-Medication-XigduoXR"/>
        <meta>
          <profile value="http://fhir.ch/ig/ch-ips/StructureDefinition/ch-ips-medication"/>
        </meta>
        <text>
          <status value="generated"/><div xmlns="http://www.w3.org/1999/xhtml"><a name="Medication_UC2-Medication-XigduoXR"> </a><p class="res-header-id"><b>Generated Narrative: Medication UC2-Medication-XigduoXR</b></p><a name="UC2-Medication-XigduoXR"> </a><a name="hcUC2-Medication-XigduoXR"> </a><div style="display: inline-block; background-color: #d9e0e7; padding: 6px; margin: 4px; border: 1px solid #8da1b4; border-radius: 5px; line-height: 60%"><p style="margin-bottom: 0px"/><p style="margin-bottom: 0px">Profile: <a href="http://fhir.ch/ig/ch-ips/2.0.0/StructureDefinition-ch-ips-medication.html">CH IPS Medication</a></p></div><p><b>code</b>: <span title="Codes:{urn:oid:2.51.1.1 7680653770050}, {http://www.whocc.no/atc A10BD15}">Xigduo XR 5/1000 mg (Dapagliflozin + Metformin)</span></p><p><b>form</b>: <span title="Codes:{urn:oid:0.4.0.127.0.16.1.1.2.1 10221005}">Retardtablette</span></p><p><b>amount</b>: 28 Tablette<span style="background: LightGoldenRodYellow"> (Details: SNOMED CT  code732936001 = '732936001')</span>/1 Packung<span style="background: LightGoldenRodYellow"> (Details: SNOMED CT  code1681000175101 = '1681000175101')</span></p></div>
        </text>
        <code>
          <coding>
            <system value="urn:oid:2.51.1.1"/>
            <code value="7680653770050"/>
            <display value="XIGDUO XR Filmtabl 5 mg/1000 mg 28 Stk"/>
          </coding>
          <coding>
            <system value="http://www.whocc.no/atc"/>
            <code value="A10BD15"/>
            <display value="metformin and dapagliflozin"/>
          </coding>
          <text value="Xigduo XR 5/1000 mg (Dapagliflozin + Metformin)"/>
        </code>
        <form>
          <coding>
            <system value="urn:oid:0.4.0.127.0.16.1.1.2.1"/>
            <code value="10221005"/>
          </coding>
          <text value="Retardtablette"/>
        </form>
        <amount>
          <numerator>
            <value value="28"/>
            <unit value="Tablette"/>
            <system value="http://snomed.info/sct|http://snomed.info/sct/2011000195101"/>
            <code value="732936001"/>
          </numerator>
          <denominator>
            <value value="1"/>
            <unit value="Packung"/>
            <system value="http://snomed.info/sct|http://snomed.info/sct/2011000195101"/>
            <code value="1681000175101"/>
          </denominator>
        </amount>
      </Medication>
    </resource>
  </entry>
  <entry>
    <fullUrl value="http://fhir.ch/ig/emr/MedicationStatement/UC2-MedicationStatement-XigduoXR"/>
    <resource>
      <MedicationStatement>
        <id value="UC2-MedicationStatement-XigduoXR"/>
        <meta>
          <profile value="http://fhir.ch/ig/ch-emr/StructureDefinition/ch-emr-medicationstatement"/>
        </meta>
        <text>
          <status value="generated"/><div xmlns="http://www.w3.org/1999/xhtml"><a name="MedicationStatement_UC2-MedicationStatement-XigduoXR"> </a><p class="res-header-id"><b>Generated Narrative: MedicationStatement UC2-MedicationStatement-XigduoXR</b></p><a name="UC2-MedicationStatement-XigduoXR"> </a><a name="hcUC2-MedicationStatement-XigduoXR"> </a><div style="display: inline-block; background-color: #d9e0e7; padding: 6px; margin: 4px; border: 1px solid #8da1b4; border-radius: 5px; line-height: 60%"><p style="margin-bottom: 0px"/><p style="margin-bottom: 0px">Profile: <a href="StructureDefinition-ch-emr-medicationstatement.html">CH Emergency Record Medication Statement</a></p></div><p><b>status</b>: Active</p><p><b>medication</b>: <a href="Medication-UC2-Medication-XigduoXR.html">Medication XIGDUO XR Filmtabl 5 mg/1000 mg 28 Stk</a></p><p><b>subject</b>: <a href="Patient-UC2-Patient-WalterSchmid.html">Walter Schmid (official) Male, DoB: 1947-04-12 ( urn:oid:2.16.756.5.30.1.123.100.1.1.1#InsuranceCardNumber#80756012222222222222)</a></p><p><b>effective</b>: 2020-01-01 --&gt; (ongoing)</p><p><b>reasonCode</b>: <span title="Codes:">Diabetes</span></p><blockquote><p><b>dosage</b></p><p><b>sequence</b>: 1</p><p><b>timing</b>: Evening, Once</p><p><b>route</b>: <span title="Codes:{urn:oid:0.4.0.127.0.16.1.1.2.1 20053000}">zum Einnehmen</span></p><h3>DoseAndRates</h3><table class="grid"><tr><td style="display: none">-</td><td><b>Dose[x]</b></td></tr><tr><td style="display: none">*</td><td>2 Tabletten<span style="background: LightGoldenRodYellow"> (Details: SNOMED CT  code732936001 = '732936001')</span></td></tr></table></blockquote></div>
        </text>
        <status value="active"/>
        <medicationReference>
          <reference value="Medication/UC2-Medication-XigduoXR"/>
        </medicationReference>
        <subject>
          <reference value="Patient/UC2-Patient-WalterSchmid"/>
        </subject>
        <effectivePeriod>
          <start value="2020-01-01"/>
        </effectivePeriod>
        <reasonCode>
          <text value="Diabetes"/>
        </reasonCode>
        <dosage>
          <sequence value="1"/>
          <timing>
            <repeat>
              <when value="EVE"/>
            </repeat>
          </timing>
          <route>
            <coding>
              <system value="urn:oid:0.4.0.127.0.16.1.1.2.1"/>
              <code value="20053000"/>
            </coding>
            <text value="zum Einnehmen"/>
          </route>
          <doseAndRate>
            <doseQuantity>
              <value value="2"/>
              <unit value="Tabletten"/>
              <system value="http://snomed.info/sct|http://snomed.info/sct/2011000195101"/>
              <code value="732936001"/>
            </doseQuantity>
          </doseAndRate>
        </dosage>
      </MedicationStatement>
    </resource>
  </entry>
  <entry>
    <fullUrl value="http://fhir.ch/ig/emr/Medication/UC2-Medication-Epril"/>
    <resource>
      <Medication>
        <id value="UC2-Medication-Epril"/>
        <meta>
          <profile value="http://fhir.ch/ig/ch-ips/StructureDefinition/ch-ips-medication"/>
        </meta>
        <text>
          <status value="generated"/><div xmlns="http://www.w3.org/1999/xhtml"><a name="Medication_UC2-Medication-Epril"> </a><p class="res-header-id"><b>Generated Narrative: Medication UC2-Medication-Epril</b></p><a name="UC2-Medication-Epril"> </a><a name="hcUC2-Medication-Epril"> </a><div style="display: inline-block; background-color: #d9e0e7; padding: 6px; margin: 4px; border: 1px solid #8da1b4; border-radius: 5px; line-height: 60%"><p style="margin-bottom: 0px"/><p style="margin-bottom: 0px">Profile: <a href="http://fhir.ch/ig/ch-ips/2.0.0/StructureDefinition-ch-ips-medication.html">CH IPS Medication</a></p></div><p><b>code</b>: <span title="Codes:{urn:oid:2.51.1.1 7680552290024}, {http://www.whocc.no/atc C09AA02}">Epril 20 mg (Enalapril)</span></p><p><b>form</b>: <span title="Codes:{urn:oid:0.4.0.127.0.16.1.1.2.1 10219000}">Tablette</span></p><p><b>amount</b>: 30 Tablette<span style="background: LightGoldenRodYellow"> (Details: SNOMED CT  code732936001 = '732936001')</span>/1 Packung<span style="background: LightGoldenRodYellow"> (Details: SNOMED CT  code1681000175101 = '1681000175101')</span></p></div>
        </text>
        <code>
          <coding>
            <system value="urn:oid:2.51.1.1"/>
            <code value="7680552290024"/>
            <display value="EPRIL Tabl 20 mg 30 Stk"/>
          </coding>
          <coding>
            <system value="http://www.whocc.no/atc"/>
            <code value="C09AA02"/>
            <display value="enalapril"/>
          </coding>
          <text value="Epril 20 mg (Enalapril)"/>
        </code>
        <form>
          <coding>
            <system value="urn:oid:0.4.0.127.0.16.1.1.2.1"/>
            <code value="10219000"/>
          </coding>
          <text value="Tablette"/>
        </form>
        <amount>
          <numerator>
            <value value="30"/>
            <unit value="Tablette"/>
            <system value="http://snomed.info/sct|http://snomed.info/sct/2011000195101"/>
            <code value="732936001"/>
          </numerator>
          <denominator>
            <value value="1"/>
            <unit value="Packung"/>
            <system value="http://snomed.info/sct|http://snomed.info/sct/2011000195101"/>
            <code value="1681000175101"/>
          </denominator>
        </amount>
      </Medication>
    </resource>
  </entry>
  <entry>
    <fullUrl value="http://fhir.ch/ig/emr/MedicationStatement/UC2-MedicationStatement-Epril"/>
    <resource>
      <MedicationStatement>
        <id value="UC2-MedicationStatement-Epril"/>
        <meta>
          <profile value="http://fhir.ch/ig/ch-emr/StructureDefinition/ch-emr-medicationstatement"/>
        </meta>
        <text>
          <status value="generated"/><div xmlns="http://www.w3.org/1999/xhtml"><a name="MedicationStatement_UC2-MedicationStatement-Epril"> </a><p class="res-header-id"><b>Generated Narrative: MedicationStatement UC2-MedicationStatement-Epril</b></p><a name="UC2-MedicationStatement-Epril"> </a><a name="hcUC2-MedicationStatement-Epril"> </a><div style="display: inline-block; background-color: #d9e0e7; padding: 6px; margin: 4px; border: 1px solid #8da1b4; border-radius: 5px; line-height: 60%"><p style="margin-bottom: 0px"/><p style="margin-bottom: 0px">Profile: <a href="StructureDefinition-ch-emr-medicationstatement.html">CH Emergency Record Medication Statement</a></p></div><p><b>status</b>: Active</p><p><b>medication</b>: <a href="Medication-UC2-Medication-Epril.html">Medication EPRIL Tabl 20 mg 30 Stk</a></p><p><b>subject</b>: <a href="Patient-UC2-Patient-WalterSchmid.html">Walter Schmid (official) Male, DoB: 1947-04-12 ( urn:oid:2.16.756.5.30.1.123.100.1.1.1#InsuranceCardNumber#80756012222222222222)</a></p><p><b>effective</b>: 2018-01-01 --&gt; (ongoing)</p><p><b>reasonCode</b>: <span title="Codes:">Bluthochdruck</span></p><blockquote><p><b>dosage</b></p><p><b>sequence</b>: 1</p><p><b>timing</b>: Morning, Once</p><p><b>route</b>: <span title="Codes:{urn:oid:0.4.0.127.0.16.1.1.2.1 20053000}">zum Einnehmen</span></p><h3>DoseAndRates</h3><table class="grid"><tr><td style="display: none">-</td><td><b>Dose[x]</b></td></tr><tr><td style="display: none">*</td><td>1 Tablette<span style="background: LightGoldenRodYellow"> (Details: SNOMED CT  code732936001 = '732936001')</span></td></tr></table></blockquote></div>
        </text>
        <status value="active"/>
        <medicationReference>
          <reference value="Medication/UC2-Medication-Epril"/>
        </medicationReference>
        <subject>
          <reference value="Patient/UC2-Patient-WalterSchmid"/>
        </subject>
        <effectivePeriod>
          <start value="2018-01-01"/>
        </effectivePeriod>
        <reasonCode>
          <text value="Bluthochdruck"/>
        </reasonCode>
        <dosage>
          <sequence value="1"/>
          <timing>
            <repeat>
              <when value="MORN"/>
            </repeat>
          </timing>
          <route>
            <coding>
              <system value="urn:oid:0.4.0.127.0.16.1.1.2.1"/>
              <code value="20053000"/>
            </coding>
            <text value="zum Einnehmen"/>
          </route>
          <doseAndRate>
            <doseQuantity>
              <value value="1"/>
              <unit value="Tablette"/>
              <system value="http://snomed.info/sct|http://snomed.info/sct/2011000195101"/>
              <code value="732936001"/>
            </doseQuantity>
          </doseAndRate>
        </dosage>
      </MedicationStatement>
    </resource>
  </entry>
  <entry>
    <fullUrl value="http://fhir.ch/ig/emr/AllergyIntolerance/UC2-AllergyIntolerance-Penicillin"/>
    <resource>
      <AllergyIntolerance>
        <id value="UC2-AllergyIntolerance-Penicillin"/>
        <meta>
          <profile value="http://fhir.ch/ig/ch-ips/StructureDefinition/ch-ips-allergyintolerance"/>
        </meta>
        <text>
          <status value="generated"/><div xmlns="http://www.w3.org/1999/xhtml"><a name="AllergyIntolerance_UC2-AllergyIntolerance-Penicillin"> </a><p class="res-header-id"><b>Generated Narrative: AllergyIntolerance UC2-AllergyIntolerance-Penicillin</b></p><a name="UC2-AllergyIntolerance-Penicillin"> </a><a name="hcUC2-AllergyIntolerance-Penicillin"> </a><div style="display: inline-block; background-color: #d9e0e7; padding: 6px; margin: 4px; border: 1px solid #8da1b4; border-radius: 5px; line-height: 60%"><p style="margin-bottom: 0px"/><p style="margin-bottom: 0px">Profile: <a href="http://fhir.ch/ig/ch-ips/2.0.0/StructureDefinition-ch-ips-allergyintolerance.html">CH IPS AllergyIntolerance</a></p></div><p><b>clinicalStatus</b>: <span title="Codes:{http://terminology.hl7.org/CodeSystem/allergyintolerance-clinical active}">Active</span></p><p><b>verificationStatus</b>: <span title="Codes:{http://terminology.hl7.org/CodeSystem/allergyintolerance-verification confirmed}">Confirmed</span></p><p><b>type</b>: Allergy</p><p><b>category</b>: Medication</p><p><b>criticality</b>: High Risk</p><p><b>code</b>: <span title="Codes:{http://snomed.info/sct 764146007}">Penicillin</span></p><p><b>patient</b>: <a href="Patient-UC2-Patient-WalterSchmid.html">Walter Schmid (official) Male, DoB: 1947-04-12 ( urn:oid:2.16.756.5.30.1.123.100.1.1.1#InsuranceCardNumber#80756012222222222222)</a></p><h3>Reactions</h3><table class="grid"><tr><td style="display: none">-</td><td><b>Manifestation</b></td><td><b>Severity</b></td></tr><tr><td style="display: none">*</td><td><span title="Codes:{http://snomed.info/sct 267036007}">Atemnot</span></td><td>Severe</td></tr></table></div>
        </text>
        <clinicalStatus>
          <coding>
            <system value="http://terminology.hl7.org/CodeSystem/allergyintolerance-clinical"/>
            <code value="active"/>
          </coding>
        </clinicalStatus>
        <verificationStatus>
          <coding>
            <system value="http://terminology.hl7.org/CodeSystem/allergyintolerance-verification"/>
            <code value="confirmed"/>
          </coding>
        </verificationStatus>
        <type value="allergy"/>
        <category value="medication"/>
        <criticality value="high"/>
        <code>
          <coding>
            <system value="http://snomed.info/sct"/>
            <version value="http://snomed.info/sct/2011000195101"/>
            <code value="764146007"/>
          </coding>
        </code>
        <patient>
          <reference value="Patient/UC2-Patient-WalterSchmid"/>
        </patient>
        <reaction>
          <manifestation>
            <coding>
              <system value="http://snomed.info/sct"/>
              <version value="http://snomed.info/sct/2011000195101"/>
              <code value="267036007"/>
            </coding>
            <text value="Atemnot"/>
          </manifestation>
          <severity value="severe"/>
        </reaction>
      </AllergyIntolerance>
    </resource>
  </entry>
  <entry>
    <fullUrl value="http://fhir.ch/ig/emr/Observation/UC2-PhysicalDisability-Aphasie"/>
    <resource>
      <Observation>
        <id value="UC2-PhysicalDisability-Aphasie"/>
        <meta>
          <profile value="http://fhir.ch/ig/ch-emr/StructureDefinition/ch-emr-observation-physical-disability"/>
        </meta>
        <text>
          <status value="generated"/><div xmlns="http://www.w3.org/1999/xhtml"><a name="Observation_UC2-PhysicalDisability-Aphasie"> </a><p class="res-header-id"><b>Generated Narrative: Observation UC2-PhysicalDisability-Aphasie</b></p><a name="UC2-PhysicalDisability-Aphasie"> </a><a name="hcUC2-PhysicalDisability-Aphasie"> </a><div style="display: inline-block; background-color: #d9e0e7; padding: 6px; margin: 4px; border: 1px solid #8da1b4; border-radius: 5px; line-height: 60%"><p style="margin-bottom: 0px"/><p style="margin-bottom: 0px">Profile: <a href="StructureDefinition-ch-emr-observation-physical-disability.html">CH Emergency Record Physical Disability Observation</a></p></div><p><b>status</b>: Final</p><p><b>category</b>: <span title="Codes:{http://terminology.hl7.org/CodeSystem/observation-category exam}">Exam</span></p><p><b>code</b>: <span title="Codes:{http://snomed.info/sct 87486003}">Aphasie</span></p><p><b>subject</b>: <a href="Patient-UC2-Patient-WalterSchmid.html">Walter Schmid (official) Male, DoB: 1947-04-12 ( urn:oid:2.16.756.5.30.1.123.100.1.1.1#InsuranceCardNumber#80756012222222222222)</a></p><p><b>effective</b>: 2023-03-01</p></div>
        </text>
        <status value="final"/>
        <category>
          <coding>
            <system value="http://terminology.hl7.org/CodeSystem/observation-category"/>
            <code value="exam"/>
          </coding>
        </category>
        <code>
          <coding>
            <system value="http://snomed.info/sct"/>
            <version value="http://snomed.info/sct/2011000195101"/>
            <code value="87486003"/>
          </coding>
          <text value="Aphasie"/>
        </code>
        <subject>
          <reference value="Patient/UC2-Patient-WalterSchmid"/>
        </subject>
        <effectiveDateTime value="2023-03-01"/>
      </Observation>
    </resource>
  </entry>
  <entry>
    <fullUrl value="http://fhir.ch/ig/emr/DocumentReference/UC2-DocumentReference-Patientenverfuegung"/>
    <resource>
      <DocumentReference>
        <id value="UC2-DocumentReference-Patientenverfuegung"/>
        <meta>
          <profile value="http://fhir.ch/ig/ch-emr/StructureDefinition/ch-emr-documentreference-advance-directive"/>
        </meta>
        <text>
          <status value="generated"/><div xmlns="http://www.w3.org/1999/xhtml"><a name="DocumentReference_UC2-DocumentReference-Patientenverfuegung"> </a><p class="res-header-id"><b>Generated Narrative: DocumentReference UC2-DocumentReference-Patientenverfuegung</b></p><a name="UC2-DocumentReference-Patientenverfuegung"> </a><a name="hcUC2-DocumentReference-Patientenverfuegung"> </a><div style="display: inline-block; background-color: #d9e0e7; padding: 6px; margin: 4px; border: 1px solid #8da1b4; border-radius: 5px; line-height: 60%"><p style="margin-bottom: 0px"/><p style="margin-bottom: 0px">Profile: <a href="StructureDefinition-ch-emr-documentreference-advance-directive.html">CH Emergency Record Advance Directive DocumentReference</a></p></div><p><b>status</b>: Current</p><p><b>type</b>: <span title="Codes:{http://loinc.org 75320-2}">Advance directive</span></p><p><b>category</b>: <span title="Codes:{http://snomed.info/sct 1264561001}">Living will (record artifact)</span></p><p><b>subject</b>: <a href="Patient-UC2-Patient-WalterSchmid.html">Walter Schmid (official) Male, DoB: 1947-04-12 ( urn:oid:2.16.756.5.30.1.123.100.1.1.1#InsuranceCardNumber#80756012222222222222)</a></p><p><b>date</b>: 2022-04-20 11:00:00+0200</p><p><b>author</b>: <a href="Patient-UC2-Patient-WalterSchmid.html">Walter Schmid (official) Male, DoB: 1947-04-12 ( urn:oid:2.16.756.5.30.1.123.100.1.1.1#InsuranceCardNumber#80756012222222222222)</a></p><p><b>custodian</b>: <a href="Organization-UC2-Organization-Hausarztpraxis.html">Organization Hausarztpraxis UC2</a></p><p><b>description</b>: Original der Patientenverfügung liegt bei der Hausarztpraxis und kann dort angefordert werden.</p><blockquote><p><b>content</b></p><h3>Attachments</h3><table class="grid"><tr><td style="display: none">-</td><td><b>Language</b></td><td><b>Title</b></td></tr><tr><td style="display: none">*</td><td>German (Switzerland)</td><td>Patientenverfügung — bei Hausarztpraxis hinterlegt</td></tr></table></blockquote></div>
        </text>
        <status value="current"/>
        <type>
          <coding>
            <system value="http://loinc.org"/>
            <code value="75320-2"/>
          </coding>
        </type>
        <category>
          <coding>
            <system value="http://snomed.info/sct"/>
            <version value="http://snomed.info/sct/2011000195101"/>
            <code value="1264561001"/>
          </coding>
        </category>
        <subject>
          <reference value="Patient/UC2-Patient-WalterSchmid"/>
        </subject>
        <date value="2022-04-20T11:00:00+02:00"/>
        <author>
          <reference value="Patient/UC2-Patient-WalterSchmid"/>
        </author>
        <custodian>
          <reference value="Organization/UC2-Organization-Hausarztpraxis"/>
        </custodian>
        <description value="Original der Patientenverfügung liegt bei der Hausarztpraxis und kann dort angefordert werden."/>
        <content>
          <attachment>
            <language value="de-CH"/>
            <title value="Patientenverfügung — bei Hausarztpraxis hinterlegt"/>
          </attachment>
        </content>
      </DocumentReference>
    </resource>
  </entry>
</Bundle>